Workbook

Sheet Worst Case
A1: WORST CASE | H1: OVERVIEW | S1: MERIT SHOP | AG1: AI COSTING
A2: SCENARIO INPUTS
A3: Total monthly users | B3: 120000
A4: Monthly Elite users | B4: 0.009 | E4: MAU tier distributions | F4: Free | G4: Elite | J4: MAU's | K4: =$B$3 -> 120000 | O4: Shop Prices | T4: Cost of features in Merits | Z4: Tokens per run - Input # | AD4: Tokens per run - Output # | AH4: Tokens per run - Cache Write # | AL4: Tokens per run - Cache Read #
A5: Annual Elite users | B5: 0.001 | E5: Monthly % | F5: =1-$B$4-$B$5 -> 0.99 | G5: =$B$4 -> 0.009 | O5: Count | P5: Price | Q5: Price per merit | T5: Features | U5: Free | V5: Elite | Z5: Features | AA5: Free | AB5: Elite | AD5: Features | AE5: Free | AF5: Elite | AH5: Features | AI5: Free | AJ5: Elite | AL5: Features | AM5: Free | AN5: Elite
E6: Annual % | F6: - | G6: =$B$5 -> 0.001 | J6: Monthly cost of plans | O6: ='Simple Inputs'!$E$27 -> 3 | P6: ='Simple Inputs'!$F$27 -> 1.99 | Q6: =P6/O6 -> 0.66333333 | T6: Resume Analysis | U6: 3 | V6: 3 | Z6: Resume Analysis | AA6: 5100 | AB6: 20000 | AD6: Resume Analysis | AE6: 4300 | AF6: 25000 | AH6: Resume Analysis | AI6: 0 | AJ6: 0 | AL6: Resume Analysis | AM6: 0 | AN6: 0
A7: MONTHLY RESULTS | E7: Monthly # | F7: =FLOOR(F5*$K$4, 1) -> 118800 | G7: =FLOOR(G5*$K$4, 1) -> 1080 | J7: Tier | K7: Free | L7: Elite | O7: ='Simple Inputs'!$E$28 -> 10 | P7: ='Simple Inputs'!$F$28 -> 4.99 | Q7: =P7/O7 -> 0.499 | T7: Career Compass | U7: 3 | V7: 3 | Z7: Linkedin Grader | AA7: 4600 | AB7: 1400 | AD7: Linkedin Grader | AE7: 5200 | AF7: 4700 | AH7: Linkedin Grader | AI7: 0 | AJ7: 4700 | AL7: Linkedin Grader | AM7: 0 | AN7: 0
A8: Revenue | B8: =$F$26 -> 26258.726 | E8: Annual # | F8: - | G8: =FLOOR(G6*$K$4, 1) -> 120 | J8: Cost (Monthly plan) | K8: - | L8: ='Simple Inputs'!$E$13 -> 16.99 | O8: ='Simple Inputs'!$E$29 -> 25 | P8: ='Simple Inputs'!$F$29 -> 9.99 | Q8: =P8/O8 -> 0.3996 | T8: Linkedin Grader | U8: 3 | V8: 3 | Z8: Career Compass | AA8: 5300 | AB8: 14000 | AD8: Career Compass | AE8: 2500 | AF8: 6100 | AH8: Career Compass | AI8: 0 | AJ8: 0 | AL8: Career Compass | AM8: 0 | AN8: 0
A9: Payment losses | B9: =-$F$27 -> 2182.297 | E9: Annual # (monthly equivalent) | F9: - | G9: =FLOOR(G8/12, 1) -> 10 | J9: Cost (Annual plan) | K9: - | L9: ='Simple Inputs'!$E$14/12 -> 14.165833 | O9: ='Simple Inputs'!$E$30 -> 50 | P9: ='Simple Inputs'!$F$30 -> 17.99 | Q9: =P9/O9 -> 0.3598 | T9: Recruiting Lens | U9: - | V9: 5 | Z9: Recruiting Lens | AA9: - | AB9: 13000 | AD9: Recruiting Lens | AE9: - | AF9: 22000 | AH9: Recruiting Lens | AI9: - | AJ9: 0 | AL9: Recruiting Lens | AM9: - | AN9: 0
A10: Stripe fees | B10: =-$F$28 -> 1692.366 | T10: Interview Prep Coach | U10: - | V10: - | Z10: Interview Prep Coach | AA10: - | AB10: - | AD10: Interview Prep Coach | AE10: - | AF10: - | AH10: Interview Prep Coach (standard) | AI10: - | AJ10: - | AL10: Interview Prep Coach | AM10: - | AN10: -
A11: AI costs | B11: =-$F$29 -> 14941.115 | E11: Max merit use/ month / user | J11: Stripe fees | Z11: TOTAL IINPUT TOKENS | AA11: =SUM(AA6:AA10) -> 15000 | AB11: =SUM(AB6:AB10) -> 48400 | AD11: TOTAL OUTPUT TOKENS | AE11: =SUM(AE6:AE10) -> 12000 | AF11: =SUM(AF6:AF9) -> 57800 | AH11: TOTAL CACHE-WRITE TOKENS | AI11: =SUM(AI6:AI8) -> 0 | AJ11: =SUM(AJ6:AJ9) -> 4700 | AL11: TOTAL CACHE-READ TOKENS | AM11: =SUM(AM6:AM10) -> 0 | AN11: =SUM(AN6:AN10) -> 0
A12: Document processing | B12: =-$F$30 -> 125.952 | E12: Membership | F12: Max merits / month | G12: Max cost | H12: Margin | J12: Fee type | K12: Value
A13: Software & infrastructure | B13: =-$F$31 -> 151.14 | E13: Free | F13: 10 | G13: =(AA30*AM15)+(AA31*AM16)+(AA32*AM17) -> -0.075 | H13: - | J13: Variable fee | K13: ='Simple Inputs'!$E$10 -> 0.029 | O13: Shop Assumptions - % | T13: Shop Assumptions - $ Charged | Z13: Cost per run - Input $ | AD13: Cost per run - Output $ | AH13: Cost per run - Cache Total $ | AL13: Cost per run - TOTAL $
A14: Total monthly costs | B14: =$F$32 -> 19092.87 | E14: Elite | F14: 150 | G14: =(AB$30*AN15)+(AB$31*AN16)+(AB$32*AN17)+(AB$33*AN18) -> -3.8063 | H14: =(L8+G14)/L8 -> 0.77596822 | J14: Fixed fee | K14: ='Simple Inputs'!$E$11 -> 0.3 | O14: Tier | P14: Free | Q14: Elite | R14: Total | T14: Tier | U14: Free | V14: Elite | W14: Total | Z14: Features | AA14: Free | AB14: Elite | AD14: Features | AE14: Free | AF14: Elite | AH14: Features | AI14: Free | AJ14: Elite | AL14: Features | AM14: Free | AN14: Elite
A15: Net profit | B15: =$F$36 -> 7165.8558 | O15: 3 Merits | P15: 0.01 | Q15: 0.0038 | R15: =SUM(P15:Q15) -> 0.0138 | T15: 3 Merits | U15: =(P24*P6) -> 2364.12 | V15: =Q24*$P6 -> 9.0744 | W15: =SUM(U15:V15) -> 2373.1944 | Z15: Resume Analysis | AA15: =AA6*$AF$29*-1 -> -0.0051 | AB15: =AB6*$AF$29*-1 -> -0.02 | AD15: Resume Analysis | AE15: =AE6*$AF$32*-1 -> -0.0215 | AF15: =AF6*$AF$32*-1 -> -0.125 | AH15: Resume Analysis | AI15: =-(AI6*$AF$30+AM6*$AF$31) -> 0 | AJ15: =-(AJ6*$AF$30+AN6*$AF$31) -> 0 | AL15: Resume Analysis | AM15: =AI15+AE15+AA15 -> -0.0266 | AN15: =AJ15+AF15+AB15 -> -0.145
A16: Profit margin | B16: =$F$37 -> 0.27289427 | E16: Stripe & AI Cost | O16: 10 Merits | P16: 0.003 | Q16: 0.0012 | R16: =SUM(P16:Q16) -> 0.0042 | T16: 10 Merits | U16: =P25*P7 -> 1778.436 | V16: =Q25*$P7 -> 7.1856 | W16: =SUM(U16:V16) -> 1785.6216 | Z16: Linkedin Grader | AA16: =AA7*$AF$29*-1 -> -0.0046 | AB16: =AB7*$AF$29*-1 -> -0.0014 | AD16: Linkedin Grader | AE16: =AE7*$AF$32*-1 -> -0.026 | AF16: =AF7*$AF$32*-1 -> -0.0235 | AH16: Linkedin Grader | AI16: =-(AI7*$AF$30+AM7*$AF$31) -> 0 | AJ16: =-(AJ7*$AF$30+AN7*$AF$31) -> -0.005875 | AL16: Linkedin Grader | AM16: =AI16+AE16+AA16 -> -0.0306 | AN16: =AJ16+AF16+AB16 -> -0.030775
A17: Founder take-home | B17: =$F$40 -> 2364.7324 | E17: Transaction type | F17: Transactions/month | G17: Average charge | H17: Gross revenue | I17: Stripe fees | J17: AI cost | K17: Profit | O17: 25 Merits | P17: 0.001 | Q17: 0.0004 | R17: =SUM(P17:Q17) -> 0.0014 | T17: 25 Merits | U17: =P26*P8 -> 1186.812 | V17: =Q26*$P8 -> 4.7952 | W17: =SUM(U17:V17) -> 1191.6072 | Z17: Career Compass | AA17: =AA8*$AF$29*-1 -> -0.0053 | AB17: =AB8*$AF$29*-1 -> -0.014 | AD17: Career Compass | AE17: =AE8*$AF$32*-1 -> -0.0125 | AF17: =AF8*$AF$32*-1 -> -0.0305 | AH17: Career Compass | AI17: =-(AI8*$AF$30+AM8*$AF$31) -> 0 | AJ17: =-(AJ8*$AF$30+AN8*$AF$31) -> 0 | AL17: Career Compass | AM17: =AI17+AE17+AA17 -> -0.0178 | AN17: =AJ17+AF17+AB17 -> -0.0445
E18: Free tier usage | F18: 0 | G18: 0 | H18: 0 | I18: 0 | J18: =F7*G13 -> -8910 | K18: =SUM(H18, I18, J18) -> -8910 | O18: 50 Merits | P18: 0.0004 | Q18: 0.0002 | R18: =SUM(P18:Q18) -> 0.0006 | T18: 50 Merits | U18: =P27*P9 -> 854.8848 | V18: =Q27*$P9 -> 4.3176 | W18: =SUM(U18:V18) -> 859.2024 | Z18: Recruiting Lens | AA18: - | AB18: =AB9*$AF$29*-1 -> -0.013 | AD18: Recruiting Lens | AE18: - | AF18: =AF9*$AF$32*-1 -> -0.11 | AH18: Recruiting Lens | AI18: - | AJ18: =-(AJ9*$AF$30+AN9*$AF$31) -> 0 | AL18: Recruiting Lens | AM18: - | AN18: =AJ18+AF18+AB18 -> -0.123
E19: Monthly Elite subscriptions | F19: =G7 -> 1080 | G19: =L8 -> 16.99 | H19: =G19*F19 -> 18349.2 | I19: =SUM(H19*K13*-1, $K$14*F19*-1) -> -856.1268 | J19: =G14*G7 -> -4110.804 | K19: =SUM(H19, I19, J19) -> 13382.269 | O19: Total | P19: =SUM(P15:P18) -> 0.0144 | Q19: =SUM(Q15:Q18) -> 0.0056 | R19: =SUM(R15:R18) -> 0.02 | T19: Total | U19: =SUM(U15:U18) -> 6184.2528 | V19: =SUM(V15:V18) -> 25.3728 | W19: =SUM(W15:W18) -> 6209.6256 | Z19: Interview Prep Coach | AA19: - | AB19: - | AD19: Interview Prep Coach (standard) | AE19: - | AF19: - | AH19: Interview Prep Coach (standard) | AI19: - | AJ19: - | AL19: Interview Prep Coach (standard) | AM19: - | AN19: -
E20: Annual Elite subscriptions | F20: =G9 -> 10 | G20: ='Simple Inputs'!$E$14 -> 169.99 | H20: =G20*F20 -> 1699.9 | I20: =SUM(H20*K13*-1, $K$14*F20*-1) -> -52.2971 | J20: =G14*G8 -> -456.756 | K20: =SUM(H20, I20, J20) -> 1190.8469 | Z20: TOTAL IINPUT COST | AA20: =SUM(AA15:AA17) -> -0.015 | AB20: =SUM(AB15:AB19) -> -0.0484 | AD20: TOTAL OUTPUT COST | AE20: =SUM(AE15:AE17) -> -0.06 | AF20: =SUM(AF15:AF18) -> -0.289 | AH20: TOTAL CACHE COST | AI20: =SUM(AI15:AI17) -> 0 | AJ20: =SUM(AJ15:AJ18) -> -0.005875 | AL20: TOTAL COST | AM20: =SUM(AM15:AM17) -> -0.075 | AN20: =SUM(AN15:AN18) -> -0.343275
E21: Merit shop purchases | F21: =R28 -> 1717.44 | G21: =W19/R28 -> 3.6156288 | H21: =G21*F21 -> 6209.6256 | I21: =SUM(H21*K13*-1, $K$14*F21*-1) -> -695.31114 | J21: =SUMPRODUCT($P$24:$P$27,$O$6:$O$9)*$AA$37+SUMPRODUCT($Q$24:$Q$27,$O$6:$O$9)*$AB$37 -> -105.27155 | K21: =SUM(H21, I21, J21) -> 5409.0429
E22: TOTAL | F22: =SUM(F19:F21) -> 2807.44 | H22: =SUM(H19:H21) -> 26258.726 | I22: =SUM(I18:I21) -> -1603.735 | J22: =SUM(J18:J21) -> -13582.832 | K22: =SUM(K18:K21) -> 11072.159 | O22: Shop Assumptions - Users | T22: Shop Assumptions - $ Profit | Z22: OCR COST MODEL BY TIER
O23: Tier | P23: Free | Q23: Elite | R23: Total | T23: Tier | U23: Free | V23: Elite | W23: Total | Z23: Tier | AA23: Resume Users | AB23: Resume Uploads / User | AC23: Resume Documents | AD23: Resume OCR Rate | AE23: Resume Pages / Doc | AF23: Resume OCR Pages | AG23: LinkedIn Users | AH23: LinkedIn Uploads / User | AI23: LinkedIn Documents | AJ23: LinkedIn OCR Rate | AK23: LinkedIn Pages / Doc | AL23: LinkedIn OCR Pages | AM23: Blended Cost / Page | AN23: Monthly OCR Cost
E24: Monthly Model | O24: 3 Merits | P24: =P15*$F$7 -> 1188 | Q24: =Q15*(G7+G8) -> 4.56 | R24: =SUM(P24:Q24) -> 1192.56 | T24: 3 Merits | U24: =IF(P24 = 0, 0, (P24*($P6*(1-$P$33)-$P$34-($O6*((-1*$G$13)/$AA$36))))) -> 1909.4605 | V24: =IF(Q24 = 0, 0, (Q24*($P6*(1-$P$33)-$P$34-($O6*((-1*$G$14)/$AB$36))))) -> 7.0961078 | W24: =SUM(U24:V24) -> 1916.5566 | Z24: Free | AA24: =$F$7 -> 118800 | AB24: ='Simple Inputs'!$E$21 -> 1 | AC24: =AA24*AB24 -> 118800 | AD24: ='Simple Inputs'!$E$17 -> 0.1 | AE24: ='Simple Inputs'!$E$18 -> 2 | AF24: =AC24*AD24*AE24 -> 23760 | AG24: =$F$7 -> 118800 | AH24: ='Simple Inputs'!$E$23 -> 0.1 | AI24: =AG24*AH24 -> 11880 | AJ24: ='Simple Inputs'!$E$19 -> 0.1 | AK24: ='Simple Inputs'!$E$20 -> 6 | AL24: =AI24*AJ24*AK24 -> 7128 | AM24: ='Simple Inputs'!$E$38 -> 0.004 | AN24: =(AF24+AL24)*AM24 -> 123.552
E25: Line Item | F25: Monthly Amount | G25: Annualized / KPI | H25: Classification | I25: Input Status | O25: 10 Merits | P25: =P16*F7 -> 356.4 | Q25: =Q16*(G7+G8) -> 1.44 | R25: =SUM(P25:Q25) -> 357.84 | T25: 10 Merits | U25: =IF(P25 = 0, 0, (P25*($P7*(1-$P$33)-$P$34-($O7*((-1*$G$13)/$AA$36))))) -> 1590.2414 | V25: =IF(Q25 = 0, 0, (Q25*($P7*(1-$P$33)-$P$34-($O7*((-1*$G$14)/$AB$36))))) -> 6.1798128 | W25: =SUM(U25:V25) -> 1596.4212 | Z25: Elite | AA25: =SUM($G$7:$G$8) -> 1200 | AB25: ='Simple Inputs'!$E$22 -> 1 | AC25: =AA25*AB25 -> 1200 | AD25: ='Simple Inputs'!$E$17 -> 0.1 | AE25: ='Simple Inputs'!$E$18 -> 2 | AF25: =AC25*AD25*AE25 -> 240 | AG25: =SUM($G$7:$G$8) -> 1200 | AH25: ='Simple Inputs'!$E$24 -> 0.5 | AI25: =AG25*AH25 -> 600 | AJ25: ='Simple Inputs'!$E$19 -> 0.1 | AK25: ='Simple Inputs'!$E$20 -> 6 | AL25: =AI25*AJ25*AK25 -> 360 | AM25: ='Simple Inputs'!$E$39 -> 0.004 | AN25: =(AF25+AL25)*AM25 -> 2.4
E26: Gross revenue | F26: =$H$22 -> 26258.726 | G26: =F26*12 -> 315104.71 | H26: Revenue | I26: Scenario formula | O26: 25 Merits | P26: =P17*$F$7 -> 118.8 | Q26: =Q17*(G7+G8) -> 0.48 | R26: =SUM(P26:Q26) -> 119.28 | T26: 25 Merits | U26: =IF(P26 = 0, 0, (P26*($P8*(1-$P$33)-$P$34-($O8*((-1*$G$13)/$AA$36))))) -> 1092.0045 | V26: =IF(Q26 = 0, 0, (Q26*($P8*(1-$P$33)-$P$34-($O8*((-1*$G$14)/$AB$36))))) -> 4.2076352 | W26: =SUM(U26:V26) -> 1096.2121 | Z26: Total | AA26: =SUM(AA24:AA25) -> 120000 | AB26: - | AC26: =SUM(AC24:AC25) -> 120000 | AD26: - | AE26: - | AF26: =SUM(AF24:AF25) -> 24000 | AG26: =SUM(AG24:AG25) -> 120000 | AH26: - | AI26: =SUM(AI24:AI25) -> 12480 | AJ26: - | AK26: - | AL26: =SUM(AL24:AL25) -> 7488 | AM26: - | AN26: =SUM(AN24:AN25) -> 125.952
E27: Failed payments, refunds, and chargebacks | F27: =SUM($S$41,$S$43,$S$45) -> -2182.297 | G27: =F27*12 -> -26187.564 | H27: Cost | I27: Estimate dependent | O27: 50 Merits | P27: =P18*$F$7 -> 47.52 | Q27: =Q18*(G7+G8) -> 0.24 | R27: =SUM(P27:Q27) -> 47.76 | T27: 50 Merits | U27: =IF(P27 = 0, 0, (P27*($P9*(1-$P$33)-$P$34-($O9*((-1*$G$13)/$AA$36))))) -> 796.03714 | V27: =IF(Q27 = 0, 0, (Q27*($P9*(1-$P$33)-$P$34-($O9*((-1*$G$14)/$AB$36))))) -> 3.8158856 | W27: =SUM(U27:V27) -> 799.85303
E28: Stripe processing, fixed, dispute, and Billing fees | F28: =SUM($S$47:$S$50) -> -1692.366 | G28: =F28*12 -> -20308.392 | H28: Cost | I28: Official rates; mix estimated | O28: Total | P28: =SUM(P24:P27) -> 1710.72 | Q28: =SUM(Q24:Q27) -> 6.72 | R28: =SUM(R24:R27) -> 1717.44 | T28: Total | U28: =SUM(U24:U27) -> 5387.7435 | V28: =SUM(V24:V27) -> 21.299441 | W28: =SUM(W24:W27) -> 5409.0429 | Z28: Assumed usage distribution | AD28: AI Information | AH28: VENDOR COST DETAIL
E29: AI inference including retry/failure overhead | F29: =$J$22*(1+'Simple Inputs'!$E$9) -> -14941.115 | G29: =F29*12 -> -179293.38 | H29: Cost | I29: Estimate dependent | Z29: Features | AA29: Free (10 merits) | AB29: Elite (150 merits) | AD29: Input cost | AE29: $1/1M Input Tokens | AF29: =1/1000000 -> 1e-06 | AH29: Component | AI29: Monthly Cost | AJ29: Calculation
E30: OCR processing | F30: =-$AN$26 -> -125.952 | G30: =F30*12 -> -1511.424 | H30: Cost | I30: Estimate dependent | Z30: Resume Analysis | AA30: 1 | AB30: 13 | AD30: Cache write cost | AE30: $1.25/1M Cache-Write Tokens | AF30: =1.25/1000000 -> 1.25e-06 | AH30: Supabase Pro base | AI30: ='Simple Inputs'!$P$46 -> 25 | AJ30: Central base plan
E31: Platform, domain, and developer tools | F31: =-$AI$37 -> -151.14 | G31: =F31*12 -> -1813.68 | H31: Cost | I31: Source backed; usage estimated | O31: Stripe fees | T31: Shop Prices | Z31: Linkedin Grader | AA31: 1 | AB31: 12 | AD31: Cache read cost | AE31: $0.10/1M Cache-Read Tokens | AF31: =0.1/1000000 -> 1e-07 | AH31: Supabase MAU overage | AI31: =IF('Simple Inputs'!$F$47="Yes",MAX(0,$K$4-'Simple Inputs'!$M$47)*'Simple Inputs'!$N$47,0) -> 65 | AJ31: Scenario MAU above allowance
E32: Total modeled cost | F32: =-SUM(F27:F31) -> 19092.87 | G32: =F32*12 -> 229114.44 | H32: KPI | I32: Calculated | O32: Fee type | P32: Value | T32: Count | U32: Price | Z32: Career Compass | AA32: 1 | AB32: 10 | AD32: Output cost | AE32: $5/1M Output Tokens | AF32: 5e-06 | AH32: Supabase other dimensions | AI32: =SUM('Simple Inputs'!$P$48:$P$55) -> 0 | AJ32: Central reference usage schedule
E33: Total modeled cost per MAU | F33: =IFERROR(F32/$K$4,0) -> 0.15910725 | G33: =F33 -> 0.15910725 | H33: KPI | I33: Calculated | O33: Variable fee | P33: ='Simple Inputs'!$E$10 -> 0.029 | T33: ='Simple Inputs'!$E$27 -> 3 | U33: ='Simple Inputs'!$F$27 -> 1.99 | Z33: Recruiting Lens | AA33: - | AB33: 9 | AD33: Model used for all features | AE33: claude-haiku-4-5-20251001 | AH33: Vercel Pro and usage | AI33: =SUM('Simple Inputs'!$P$56:$P$62) -> 20 | AJ33: Central reference usage schedule
E34: AI plus OCR cost per MAU | F34: =IFERROR(-(F29+F30)/$K$4,0) -> 0.12555889 | G34: =F34 -> 0.12555889 | H34: KPI | I34: Estimate dependent | O34: Fixed fee | P34: ='Simple Inputs'!$E$11 -> 0.3 | T34: ='Simple Inputs'!$E$28 -> 10 | U34: ='Simple Inputs'!$F$28 -> 4.99 | Z34: Interview Prep Coach | AA34: - | AB34: - | AH34: Domain | AI34: ='Simple Inputs'!$P$63 -> 1.14 | AJ34: Date-aware current term / renewal
E35: Vendor cost per MAU | F35: =IFERROR(-F31/$K$4,0) -> 0.0012595 | G35: =F35 -> 0.0012595 | H35: KPI | I35: Calculated | T35: ='Simple Inputs'!$E$29 -> 25 | U35: ='Simple Inputs'!$F$29 -> 9.99 | Z35: TOTAL RUNS | AA35: =SUM(AA30:AA34) -> 3 | AB35: =SUM(AB30:AB34) -> 44 | AH35: Developer tools | AI35: =SUM('Simple Inputs'!$P$64:$P$65) -> 40 | AJ35: Monthly subscriptions
E36: NET OPERATING PROFIT | F36: =SUM(F26:F31) -> 7165.8558 | G36: =F36*12 -> 85990.27 | H36: Profit | I36: Calculated | T36: ='Simple Inputs'!$E$30 -> 50 | U36: ='Simple Inputs'!$F$30 -> 17.99 | Z36: TOTAL MERITS | AA36: =(AA30*U6)+(AA31*U7)+(AA32*U8) -> 9 | AB36: =(AB30*V6)+(AB31*V7)+(AB32*V8)+(AB33*V9) -> 150 | AH36: Other active recurring services | AI36: =SUM('Simple Inputs'!$P$66:$P$67,'Simple Inputs'!$P$71) -> 0 | AJ36: Only explicitly activated rows
E37: Net operating margin | F37: =IFERROR(F36/F26,0) -> 0.27289427 | G37: =F37 -> 0.27289427 | H37: KPI | I37: Calculated | Z37: COST PER MERIT | AA37: =$G$13/AA36 -> -0.0083333333 | AB37: =$G$14/AB36 -> -0.025375333 | AH37: TOTAL VENDOR COST | AI37: =SUM(AI30:AI36) -> 151.14 | AJ37: Sum of vendor components
E38: Founder share before tax | F38: =F36/'Simple Inputs'!$E$16 -> 3582.9279 | G38: =F38*12 -> 42995.135 | H38: Founder | I38: Calculated | O38: PAYMENT LOSS
E39: Founder tax reserve | F39: =-MAX(0,F38)*'Simple Inputs'!$E$15 -> -1218.1955 | G39: =F39*12 -> -14618.346 | H39: Founder | I39: Existing assumption | O39: Line Item | P39: Monthly Subs | Q39: Annual Subs | R39: Merit Shop | S39: Total | T39: Calculation Logic
E40: FOUNDER TAKE-HOME | F40: =SUM(F38:F39) -> 2364.7324 | G40: =F40*12 -> 28376.789 | H40: Founder | I40: Calculated | O40: Gross billed | P40: =$H$19 -> 18349.2 | Q40: =$H$20 -> 1699.9 | R40: =$H$21 -> 6209.6256 | S40: =SUM(P40:R40) -> 26258.726 | T40: Scenario gross billed
O41: Failed payment loss | P41: =-P40*'Simple Inputs'!$E$6 -> -917.46 | Q41: =-Q40*'Simple Inputs'!$E$6 -> -84.995 | R41: =-R40*'Simple Inputs'!$E$6 -> -310.48128 | S41: =SUM(P41:R41) -> -1312.9363 | T41: Gross × failed-payment rate
O42: Collected after failures | P42: =SUM(P40:P41) -> 17431.74 | Q42: =SUM(Q40:Q41) -> 1614.905 | R42: =SUM(R40:R41) -> 5899.1443 | S42: =SUM(P42:R42) -> 24945.789 | T42: Gross + failed loss
O43: Refund loss | P43: =-P42*'Simple Inputs'!$E$7 -> -522.9522 | Q43: =-Q42*'Simple Inputs'!$E$7 -> -48.44715 | R43: =-R42*'Simple Inputs'!$E$7 -> -176.97433 | S43: =SUM(P43:R43) -> -748.37368 | T43: Collected × refund rate
O44: Post-refund volume | P44: =SUM(P42:P43) -> 16908.788 | Q44: =SUM(Q42:Q43) -> 1566.4579 | R44: =SUM(R42:R43) -> 5722.17 | S44: =SUM(P44:R44) -> 24197.416 | T44: Collected + refund loss
O45: Chargeback principal loss | P45: =-P44*'Simple Inputs'!$E$8 -> -84.543939 | Q45: =-Q44*'Simple Inputs'!$E$8 -> -7.8322892 | R45: =-R44*'Simple Inputs'!$E$8 -> -28.61085 | S45: =SUM(P45:R45) -> -120.98708 | T45: Post-refund × chargeback rate
O46: Post-chargeback volume | P46: =SUM(P44:P45) -> 16824.244 | Q46: =SUM(Q44:Q45) -> 1558.6256 | R46: =SUM(R44:R45) -> 5693.5591 | S46: =SUM(P46:R46) -> 24076.429 | T46: Post-refund + chargeback loss
O47: Stripe variable fee | P47: =-P46*'Simple Inputs'!$E$10 -> -487.90307 | Q47: =-Q46*'Simple Inputs'!$E$10 -> -45.200141 | R47: =-R46*'Simple Inputs'!$E$10 -> -165.11322 | S47: =SUM(P47:R47) -> -698.21643 | T47: Post-chargeback volume × variable fee
O48: Stripe fixed fee | P48: =-$F$19*(1-'Simple Inputs'!$E$6)*'Simple Inputs'!$E$11 -> -307.8 | Q48: =-$F$20*(1-'Simple Inputs'!$E$6)*'Simple Inputs'!$E$11 -> -2.85 | R48: =-$F$21*(1-'Simple Inputs'!$E$6)*'Simple Inputs'!$E$11 -> -489.4704 | S48: =SUM(P48:R48) -> -800.1204 | T48: Successful transactions × fixed fee
O49: Dispute fee | P49: =-$F$19*(1-'Simple Inputs'!$E$6)*(1-'Simple Inputs'!$E$7)*'Simple Inputs'!$E$8*'Simple Inputs'!$E$12 -> -74.6415 | Q49: =-$F$20*(1-'Simple Inputs'!$E$6)*(1-'Simple Inputs'!$E$7)*'Simple Inputs'!$E$8*'Simple Inputs'!$E$12 -> -0.691125 | R49: =-$F$21*(1-'Simple Inputs'!$E$6)*(1-'Simple Inputs'!$E$7)*'Simple Inputs'!$E$8*'Simple Inputs'!$E$12 -> -118.69657 | S49: =SUM(P49:R49) -> -194.0292 | T49: Disputed transaction proxy × dispute fee
O50: Stripe Billing fee | P50: =-P46*IF('Simple Inputs'!$F$45="Yes",'Simple Inputs'!$I$45,0) -> 0 | Q50: =-Q46*IF('Simple Inputs'!$F$45="Yes",'Simple Inputs'!$I$45,0) -> 0 | R50: =-R46*IF('Simple Inputs'!$F$45="Yes",'Simple Inputs'!$I$45,0) -> 0 | S50: =SUM(P50:R50) -> 0 | T50: Post-chargeback volume × Billing rate when active
O51: Net cash after payments | P51: =SUM(P40,P41,P43,P45,P47:P50) -> 15953.899 | Q51: =SUM(Q40,Q41,Q43,Q45,Q47:Q50) -> 1509.8843 | R51: =SUM(R40,R41,R43,R45,R47:R50) -> 4920.279 | S51: =SUM(P51:R51) -> 22384.063 | T51: Gross plus every loss and fee
O52: Reconciliation variance | P52: =P51-(P40+SUM(P41,P43,P45,P47:P50)) -> 0 | Q52: =Q51-(Q40+SUM(Q41,Q43,Q45,Q47:Q50)) -> 0 | R52: =R51-(R40+SUM(R41,R43,R45,R47:R50)) -> 0 | S52: =SUM(P52:R52) -> 0 | T52: Net cash minus reconstructed waterfall

Sheet Mid Case
A1: MID CASE | H1: OVERVIEW | S1: MERIT SHOP | AG1: AI COSTING
A2: SCENARIO INPUTS
A3: Total monthly users | B3: 120000
A4: Monthly Elite users | B4: 0.034 | E4: MAU tier distributions | F4: Free | G4: Elite | J4: MAU's | K4: =$B$3 -> 120000 | O4: Shop Prices | T4: Cost of features in Merits | Z4: Tokens per run - Input # | AD4: Tokens per run - Output # | AH4: Tokens per run - Cache Write # | AL4: Tokens per run - Cache Read #
A5: Annual Elite users | B5: 0.006 | E5: Monthly % | F5: =1-$B$4-$B$5 -> 0.96 | G5: =$B$4 -> 0.034 | O5: Count | P5: Price | Q5: Price per merit | T5: Features | U5: Free | V5: Elite | Z5: Features | AA5: Free | AB5: Elite | AD5: Features | AE5: Free | AF5: Elite | AH5: Features | AI5: Free | AJ5: Elite | AL5: Features | AM5: Free | AN5: Elite
E6: Annual % | F6: - | G6: =$B$5 -> 0.006 | J6: Monthly cost of plans | O6: ='Simple Inputs'!$E$27 -> 3 | P6: ='Simple Inputs'!$F$27 -> 1.99 | Q6: =P6/O6 -> 0.66333333 | T6: Resume Analysis | U6: 3 | V6: 3 | Z6: Resume Analysis | AA6: 5100 | AB6: 20000 | AD6: Resume Analysis | AE6: 4300 | AF6: 25000 | AH6: Resume Analysis | AI6: 0 | AJ6: 0 | AL6: Resume Analysis | AM6: 0 | AN6: 0
A7: MONTHLY RESULTS | E7: Monthly # | F7: =FLOOR(F5*$K$4, 1) -> 115200 | G7: =FLOOR(G5*$K$4, 1) -> 4080 | J7: Tier | K7: Free | L7: Elite | O7: ='Simple Inputs'!$E$28 -> 10 | P7: ='Simple Inputs'!$F$28 -> 4.99 | Q7: =P7/O7 -> 0.499 | T7: Career Compass | U7: 3 | V7: 3 | Z7: Linkedin Grader | AA7: 4600 | AB7: 1400 | AD7: Linkedin Grader | AE7: 5200 | AF7: 4700 | AH7: Linkedin Grader | AI7: 0 | AJ7: 4700 | AL7: Linkedin Grader | AM7: 0 | AN7: 0
A8: Revenue | B8: =$F$26 -> 88666.114 | E8: Annual # | F8: - | G8: =FLOOR(G6*$K$4, 1) -> 720 | J8: Cost (Monthly plan) | K8: - | L8: ='Simple Inputs'!$E$13 -> 16.99 | O8: ='Simple Inputs'!$E$29 -> 25 | P8: ='Simple Inputs'!$F$29 -> 9.99 | Q8: =P8/O8 -> 0.3996 | T8: Linkedin Grader | U8: 3 | V8: 3 | Z8: Career Compass | AA8: 5300 | AB8: 14000 | AD8: Career Compass | AE8: 2500 | AF8: 6100 | AH8: Career Compass | AI8: 0 | AJ8: 0 | AL8: Career Compass | AM8: 0 | AN8: 0
A9: Payment losses | B9: =-$F$27 -> 7368.819 | E9: Annual # (monthly equivalent) | F9: - | G9: =FLOOR(G8/12, 1) -> 60 | J9: Cost (Annual plan) | K9: - | L9: ='Simple Inputs'!$E$14/12 -> 14.165833 | O9: ='Simple Inputs'!$E$30 -> 50 | P9: ='Simple Inputs'!$F$30 -> 17.99 | Q9: =P9/O9 -> 0.3598 | T9: Recruiting Lens | U9: - | V9: 5 | Z9: Recruiting Lens | AA9: - | AB9: 13000 | AD9: Recruiting Lens | AE9: - | AF9: 22000 | AH9: Recruiting Lens | AI9: - | AJ9: 0 | AL9: Recruiting Lens | AM9: - | AN9: 0
A10: Stripe fees | B10: =-$F$28 -> 4719.0703 | T10: Interview Prep Coach | U10: - | V10: - | Z10: Interview Prep Coach | AA10: - | AB10: - | AD10: Interview Prep Coach | AE10: - | AF10: - | AH10: Interview Prep Coach (standard) | AI10: - | AJ10: - | AL10: Interview Prep Coach | AM10: - | AN10: -
A11: AI costs | B11: =-$F$29 -> 17935.801 | E11: Max merit use/ month / user | J11: Stripe fees | Z11: TOTAL IINPUT TOKENS | AA11: =SUM(AA6:AA10) -> 15000 | AB11: =SUM(AB6:AB10) -> 48400 | AD11: TOTAL OUTPUT TOKENS | AE11: =SUM(AE6:AE10) -> 12000 | AF11: =SUM(AF6:AF9) -> 57800 | AH11: TOTAL CACHE-WRITE TOKENS | AI11: =SUM(AI6:AI8) -> 0 | AJ11: =SUM(AJ6:AJ9) -> 4700 | AL11: TOTAL CACHE-READ TOKENS | AM11: =SUM(AM6:AM10) -> 0 | AN11: =SUM(AN6:AN10) -> 0
A12: Document processing | B12: =-$F$30 -> 129.408 | E12: Membership | F12: Max merits / month | G12: Max cost | H12: Margin | J12: Fee type | K12: Value
A13: Software & infrastructure | B13: =-$F$31 -> 151.14 | E13: Free | F13: 10 | G13: =(AA30*AM15)+(AA31*AM16)+(AA32*AM17) -> -0.045 | H13: - | J13: Variable fee | K13: ='Simple Inputs'!$E$10 -> 0.029 | O13: Shop Assumptions - % | T13: Shop Assumptions - $ Charged | Z13: Cost per run - Input $ | AD13: Cost per run - Output $ | AH13: Cost per run - Cache Total $ | AL13: Cost per run - TOTAL $
A14: Total monthly costs | B14: =$F$32 -> 30304.238 | E14: Elite | F14: 150 | G14: =(AB$30*AN15)+(AB$31*AN16)+(AB$32*AN17)+(AB$33*AN18) -> -2.28378 | H14: =(L8+G14)/L8 -> 0.86558093 | J14: Fixed fee | K14: ='Simple Inputs'!$E$11 -> 0.3 | O14: Tier | P14: Free | Q14: Elite | R14: Total | T14: Tier | U14: Free | V14: Elite | W14: Total | Z14: Features | AA14: Free | AB14: Elite | AD14: Features | AE14: Free | AF14: Elite | AH14: Features | AI14: Free | AJ14: Elite | AL14: Features | AM14: Free | AN14: Elite
A15: Net profit | B15: =$F$36 -> 58361.876 | O15: 3 Merits | P15: 0.015 | Q15: 0.0057 | R15: =SUM(P15:Q15) -> 0.0207 | T15: 3 Merits | U15: =(P24*P6) -> 3438.72 | V15: =Q24*$P6 -> 54.4464 | W15: =SUM(U15:V15) -> 3493.1664 | Z15: Resume Analysis | AA15: =AA6*$AF$29*-1 -> -0.0051 | AB15: =AB6*$AF$29*-1 -> -0.02 | AD15: Resume Analysis | AE15: =AE6*$AF$32*-1 -> -0.0215 | AF15: =AF6*$AF$32*-1 -> -0.125 | AH15: Resume Analysis | AI15: =-(AI6*$AF$30+AM6*$AF$31) -> 0 | AJ15: =-(AJ6*$AF$30+AN6*$AF$31) -> 0 | AL15: Resume Analysis | AM15: =AI15+AE15+AA15 -> -0.0266 | AN15: =AJ15+AF15+AB15 -> -0.145
A16: Profit margin | B16: =$F$37 -> 0.65822075 | E16: Stripe & AI Cost | O16: 10 Merits | P16: 0.0045 | Q16: 0.0018 | R16: =SUM(P16:Q16) -> 0.0063 | T16: 10 Merits | U16: =P25*P7 -> 2586.816 | V16: =Q25*$P7 -> 43.1136 | W16: =SUM(U16:V16) -> 2629.9296 | Z16: Linkedin Grader | AA16: =AA7*$AF$29*-1 -> -0.0046 | AB16: =AB7*$AF$29*-1 -> -0.0014 | AD16: Linkedin Grader | AE16: =AE7*$AF$32*-1 -> -0.026 | AF16: =AF7*$AF$32*-1 -> -0.0235 | AH16: Linkedin Grader | AI16: =-(AI7*$AF$30+AM7*$AF$31) -> 0 | AJ16: =-(AJ7*$AF$30+AN7*$AF$31) -> -0.005875 | AL16: Linkedin Grader | AM16: =AI16+AE16+AA16 -> -0.0306 | AN16: =AJ16+AF16+AB16 -> -0.030775
A17: Founder take-home | B17: =$F$40 -> 19259.419 | E17: Transaction type | F17: Transactions/month | G17: Average charge | H17: Gross revenue | I17: Stripe fees | J17: AI cost | K17: Profit | O17: 25 Merits | P17: 0.0015 | Q17: 0.0006 | R17: =SUM(P17:Q17) -> 0.0021 | T17: 25 Merits | U17: =P26*P8 -> 1726.272 | V17: =Q26*$P8 -> 28.7712 | W17: =SUM(U17:V17) -> 1755.0432 | Z17: Career Compass | AA17: =AA8*$AF$29*-1 -> -0.0053 | AB17: =AB8*$AF$29*-1 -> -0.014 | AD17: Career Compass | AE17: =AE8*$AF$32*-1 -> -0.0125 | AF17: =AF8*$AF$32*-1 -> -0.0305 | AH17: Career Compass | AI17: =-(AI8*$AF$30+AM8*$AF$31) -> 0 | AJ17: =-(AJ8*$AF$30+AN8*$AF$31) -> 0 | AL17: Career Compass | AM17: =AI17+AE17+AA17 -> -0.0178 | AN17: =AJ17+AF17+AB17 -> -0.0445
E18: Free tier usage | F18: 0 | G18: 0 | H18: 0 | I18: 0 | J18: =F7*G13 -> -5184 | K18: =SUM(H18, I18, J18) -> -5184 | O18: 50 Merits | P18: 0.0006 | Q18: 0.0003 | R18: =SUM(P18:Q18) -> 0.0009 | T18: 50 Merits | U18: =P27*P9 -> 1243.4688 | V18: =Q27*$P9 -> 25.9056 | W18: =SUM(U18:V18) -> 1269.3744 | Z18: Recruiting Lens | AA18: - | AB18: =AB9*$AF$29*-1 -> -0.013 | AD18: Recruiting Lens | AE18: - | AF18: =AF9*$AF$32*-1 -> -0.11 | AH18: Recruiting Lens | AI18: - | AJ18: =-(AJ9*$AF$30+AN9*$AF$31) -> 0 | AL18: Recruiting Lens | AM18: - | AN18: =AJ18+AF18+AB18 -> -0.123
E19: Monthly Elite subscriptions | F19: =G7 -> 4080 | G19: =L8 -> 16.99 | H19: =G19*F19 -> 69319.2 | I19: =SUM(H19*K13*-1, $K$14*F19*-1) -> -3234.2568 | J19: =G14*G7 -> -9317.8224 | K19: =SUM(H19, I19, J19) -> 56767.121 | O19: Total | P19: =SUM(P15:P18) -> 0.0216 | Q19: =SUM(Q15:Q18) -> 0.0084 | R19: =SUM(R15:R18) -> 0.03 | T19: Total | U19: =SUM(U15:U18) -> 8995.2768 | V19: =SUM(V15:V18) -> 152.2368 | W19: =SUM(W15:W18) -> 9147.5136 | Z19: Interview Prep Coach | AA19: - | AB19: - | AD19: Interview Prep Coach (standard) | AE19: - | AF19: - | AH19: Interview Prep Coach (standard) | AI19: - | AJ19: - | AL19: Interview Prep Coach (standard) | AM19: - | AN19: -
E20: Annual Elite subscriptions | F20: =G9 -> 60 | G20: ='Simple Inputs'!$E$14 -> 169.99 | H20: =G20*F20 -> 10199.4 | I20: =SUM(H20*K13*-1, $K$14*F20*-1) -> -313.7826 | J20: =G14*G8 -> -1644.3216 | K20: =SUM(H20, I20, J20) -> 8241.2958 | Z20: TOTAL IINPUT COST | AA20: =SUM(AA15:AA17) -> -0.015 | AB20: =SUM(AB15:AB19) -> -0.0484 | AD20: TOTAL OUTPUT COST | AE20: =SUM(AE15:AE17) -> -0.06 | AF20: =SUM(AF15:AF18) -> -0.289 | AH20: TOTAL CACHE COST | AI20: =SUM(AI15:AI17) -> 0 | AJ20: =SUM(AJ15:AJ18) -> -0.005875 | AL20: TOTAL COST | AM20: =SUM(AM15:AM17) -> -0.075 | AN20: =SUM(AN15:AN18) -> -0.343275
E21: Merit shop purchases | F21: =R28 -> 2528.64 | G21: =W19/R28 -> 3.6175626 | H21: =G21*F21 -> 9147.5136 | I21: =SUM(H21*K13*-1, $K$14*F21*-1) -> -1023.8699 | J21: =SUMPRODUCT($P$24:$P$27,$O$6:$O$9)*$AA$37+SUMPRODUCT($Q$24:$Q$27,$O$6:$O$9)*$AB$37 -> -159.12928 | K21: =SUM(H21, I21, J21) -> 7964.5144
E22: TOTAL | F22: =SUM(F19:F21) -> 6668.64 | H22: =SUM(H19:H21) -> 88666.114 | I22: =SUM(I18:I21) -> -4571.9093 | J22: =SUM(J18:J21) -> -16305.273 | K22: =SUM(K18:K21) -> 67788.931 | O22: Shop Assumptions - Users | T22: Shop Assumptions - $ Profit | Z22: OCR COST MODEL BY TIER
O23: Tier | P23: Free | Q23: Elite | R23: Total | T23: Tier | U23: Free | V23: Elite | W23: Total | Z23: Tier | AA23: Resume Users | AB23: Resume Uploads / User | AC23: Resume Documents | AD23: Resume OCR Rate | AE23: Resume Pages / Doc | AF23: Resume OCR Pages | AG23: LinkedIn Users | AH23: LinkedIn Uploads / User | AI23: LinkedIn Documents | AJ23: LinkedIn OCR Rate | AK23: LinkedIn Pages / Doc | AL23: LinkedIn OCR Pages | AM23: Blended Cost / Page | AN23: Monthly OCR Cost
E24: Monthly Model | O24: 3 Merits | P24: =P15*$F$7 -> 1728 | Q24: =Q15*(G7+G8) -> 27.36 | R24: =SUM(P24:Q24) -> 1755.36 | T24: 3 Merits | U24: =IF(P24 = 0, 0, (P24*($P6*(1-$P$33)-$P$34-($O6*((-1*$G$13)/$AA$36))))) -> 2777.3971 | V24: =IF(Q24 = 0, 0, (Q24*($P6*(1-$P$33)-$P$34-($O6*((-1*$G$14)/$AB$36))))) -> 42.576647 | W24: =SUM(U24:V24) -> 2819.9738 | Z24: Free | AA24: =$F$7 -> 115200 | AB24: ='Simple Inputs'!$E$21 -> 1 | AC24: =AA24*AB24 -> 115200 | AD24: ='Simple Inputs'!$E$17 -> 0.1 | AE24: ='Simple Inputs'!$E$18 -> 2 | AF24: =AC24*AD24*AE24 -> 23040 | AG24: =$F$7 -> 115200 | AH24: ='Simple Inputs'!$E$23 -> 0.1 | AI24: =AG24*AH24 -> 11520 | AJ24: ='Simple Inputs'!$E$19 -> 0.1 | AK24: ='Simple Inputs'!$E$20 -> 6 | AL24: =AI24*AJ24*AK24 -> 6912 | AM24: ='Simple Inputs'!$E$38 -> 0.004 | AN24: =(AF24+AL24)*AM24 -> 119.808
E25: Line Item | F25: Monthly Amount | G25: Annualized / KPI | H25: Classification | I25: Input Status | O25: 10 Merits | P25: =P16*F7 -> 518.4 | Q25: =Q16*(G7+G8) -> 8.64 | R25: =SUM(P25:Q25) -> 527.04 | T25: 10 Merits | U25: =IF(P25 = 0, 0, (P25*($P7*(1-$P$33)-$P$34-($O7*((-1*$G$13)/$AA$36))))) -> 2313.0783 | V25: =IF(Q25 = 0, 0, (Q25*($P7*(1-$P$33)-$P$34-($O7*((-1*$G$14)/$AB$36))))) -> 37.078877 | W25: =SUM(U25:V25) -> 2350.1572 | Z25: Elite | AA25: =SUM($G$7:$G$8) -> 4800 | AB25: ='Simple Inputs'!$E$22 -> 1 | AC25: =AA25*AB25 -> 4800 | AD25: ='Simple Inputs'!$E$17 -> 0.1 | AE25: ='Simple Inputs'!$E$18 -> 2 | AF25: =AC25*AD25*AE25 -> 960 | AG25: =SUM($G$7:$G$8) -> 4800 | AH25: ='Simple Inputs'!$E$24 -> 0.5 | AI25: =AG25*AH25 -> 2400 | AJ25: ='Simple Inputs'!$E$19 -> 0.1 | AK25: ='Simple Inputs'!$E$20 -> 6 | AL25: =AI25*AJ25*AK25 -> 1440 | AM25: ='Simple Inputs'!$E$39 -> 0.004 | AN25: =(AF25+AL25)*AM25 -> 9.6
E26: Gross revenue | F26: =$H$22 -> 88666.114 | G26: =F26*12 -> 1063993.4 | H26: Revenue | I26: Scenario formula | O26: 25 Merits | P26: =P17*$F$7 -> 172.8 | Q26: =Q17*(G7+G8) -> 2.88 | R26: =SUM(P26:Q26) -> 175.68 | T26: 25 Merits | U26: =IF(P26 = 0, 0, (P26*($P8*(1-$P$33)-$P$34-($O8*((-1*$G$13)/$AA$36))))) -> 1588.3701 | V26: =IF(Q26 = 0, 0, (Q26*($P8*(1-$P$33)-$P$34-($O8*((-1*$G$14)/$AB$36))))) -> 25.245811 | W26: =SUM(U26:V26) -> 1613.6159 | Z26: Total | AA26: =SUM(AA24:AA25) -> 120000 | AB26: - | AC26: =SUM(AC24:AC25) -> 120000 | AD26: - | AE26: - | AF26: =SUM(AF24:AF25) -> 24000 | AG26: =SUM(AG24:AG25) -> 120000 | AH26: - | AI26: =SUM(AI24:AI25) -> 13920 | AJ26: - | AK26: - | AL26: =SUM(AL24:AL25) -> 8352 | AM26: - | AN26: =SUM(AN24:AN25) -> 129.408
E27: Failed payments, refunds, and chargebacks | F27: =SUM($S$41,$S$43,$S$45) -> -7368.819 | G27: =F27*12 -> -88425.828 | H27: Cost | I27: Estimate dependent | O27: 50 Merits | P27: =P18*$F$7 -> 69.12 | Q27: =Q18*(G7+G8) -> 1.44 | R27: =SUM(P27:Q27) -> 70.56 | T27: 50 Merits | U27: =IF(P27 = 0, 0, (P27*($P9*(1-$P$33)-$P$34-($O9*((-1*$G$13)/$AA$36))))) -> 1157.8722 | V27: =IF(Q27 = 0, 0, (Q27*($P9*(1-$P$33)-$P$34-($O9*((-1*$G$14)/$AB$36))))) -> 22.895314 | W27: =SUM(U27:V27) -> 1180.7675
E28: Stripe processing, fixed, dispute, and Billing fees | F28: =SUM($S$47:$S$50) -> -4719.0703 | G28: =F28*12 -> -56628.844 | H28: Cost | I28: Official rates; mix estimated | O28: Total | P28: =SUM(P24:P27) -> 2488.32 | Q28: =SUM(Q24:Q27) -> 40.32 | R28: =SUM(R24:R27) -> 2528.64 | T28: Total | U28: =SUM(U24:U27) -> 7836.7178 | V28: =SUM(V24:V27) -> 127.79665 | W28: =SUM(W24:W27) -> 7964.5144 | Z28: Assumed usage distribution | AD28: AI Information | AH28: VENDOR COST DETAIL
E29: AI inference including retry/failure overhead | F29: =$J$22*(1+'Simple Inputs'!$E$9) -> -17935.801 | G29: =F29*12 -> -215229.61 | H29: Cost | I29: Estimate dependent | Z29: Features | AA29: Free (10 merits) | AB29: Elite (150 merits) | AD29: Input cost | AE29: $1/1M Input Tokens | AF29: =1/1000000 -> 1e-06 | AH29: Component | AI29: Monthly Cost | AJ29: Calculation
E30: OCR processing | F30: =-$AN$26 -> -129.408 | G30: =F30*12 -> -1552.896 | H30: Cost | I30: Estimate dependent | Z30: Resume Analysis | AA30: 0.6 | AB30: 7.8 | AD30: Cache write cost | AE30: $1.25/1M Cache-Write Tokens | AF30: =1.25/1000000 -> 1.25e-06 | AH30: Supabase Pro base | AI30: ='Simple Inputs'!$P$46 -> 25 | AJ30: Central base plan
E31: Platform, domain, and developer tools | F31: =-$AI$37 -> -151.14 | G31: =F31*12 -> -1813.68 | H31: Cost | I31: Source backed; usage estimated | O31: Stripe fees | T31: Shop Prices | Z31: Linkedin Grader | AA31: 0.6 | AB31: 7.2 | AD31: Cache read cost | AE31: $0.10/1M Cache-Read Tokens | AF31: =0.1/1000000 -> 1e-07 | AH31: Supabase MAU overage | AI31: =IF('Simple Inputs'!$F$47="Yes",MAX(0,$K$4-'Simple Inputs'!$M$47)*'Simple Inputs'!$N$47,0) -> 65 | AJ31: Scenario MAU above allowance
E32: Total modeled cost | F32: =-SUM(F27:F31) -> 30304.238 | G32: =F32*12 -> 363650.86 | H32: KPI | I32: Calculated | O32: Fee type | P32: Value | T32: Count | U32: Price | Z32: Career Compass | AA32: 0.6 | AB32: 6 | AD32: Output cost | AE32: $5/1M Output Tokens | AF32: 5e-06 | AH32: Supabase other dimensions | AI32: =SUM('Simple Inputs'!$P$48:$P$55) -> 0 | AJ32: Central reference usage schedule
E33: Total modeled cost per MAU | F33: =IFERROR(F32/$K$4,0) -> 0.25253532 | G33: =F33 -> 0.25253532 | H33: KPI | I33: Calculated | O33: Variable fee | P33: ='Simple Inputs'!$E$10 -> 0.029 | T33: ='Simple Inputs'!$E$27 -> 3 | U33: ='Simple Inputs'!$F$27 -> 1.99 | Z33: Recruiting Lens | AA33: - | AB33: 5.4 | AD33: Model used for all features | AE33: claude-haiku-4-5-20251001 | AH33: Vercel Pro and usage | AI33: =SUM('Simple Inputs'!$P$56:$P$62) -> 20 | AJ33: Central reference usage schedule
E34: AI plus OCR cost per MAU | F34: =IFERROR(-(F29+F30)/$K$4,0) -> 0.15054341 | G34: =F34 -> 0.15054341 | H34: KPI | I34: Estimate dependent | O34: Fixed fee | P34: ='Simple Inputs'!$E$11 -> 0.3 | T34: ='Simple Inputs'!$E$28 -> 10 | U34: ='Simple Inputs'!$F$28 -> 4.99 | Z34: Interview Prep Coach | AA34: - | AB34: - | AH34: Domain | AI34: ='Simple Inputs'!$P$63 -> 1.14 | AJ34: Date-aware current term / renewal
E35: Vendor cost per MAU | F35: =IFERROR(-F31/$K$4,0) -> 0.0012595 | G35: =F35 -> 0.0012595 | H35: KPI | I35: Calculated | T35: ='Simple Inputs'!$E$29 -> 25 | U35: ='Simple Inputs'!$F$29 -> 9.99 | Z35: TOTAL RUNS | AA35: =SUM(AA30:AA34) -> 1.8 | AB35: =SUM(AB30:AB34) -> 26.4 | AH35: Developer tools | AI35: =SUM('Simple Inputs'!$P$64:$P$65) -> 40 | AJ35: Monthly subscriptions
E36: NET OPERATING PROFIT | F36: =SUM(F26:F31) -> 58361.876 | G36: =F36*12 -> 700342.51 | H36: Profit | I36: Calculated | T36: ='Simple Inputs'!$E$30 -> 50 | U36: ='Simple Inputs'!$F$30 -> 17.99 | Z36: TOTAL MERITS | AA36: =(AA30*U6)+(AA31*U7)+(AA32*U8) -> 5.4 | AB36: =(AB30*V6)+(AB31*V7)+(AB32*V8)+(AB33*V9) -> 90 | AH36: Other active recurring services | AI36: =SUM('Simple Inputs'!$P$66:$P$67,'Simple Inputs'!$P$71) -> 0 | AJ36: Only explicitly activated rows
E37: Net operating margin | F37: =IFERROR(F36/F26,0) -> 0.65822075 | G37: =F37 -> 0.65822075 | H37: KPI | I37: Calculated | Z37: COST PER MERIT | AA37: =$G$13/AA36 -> -0.0083333333 | AB37: =$G$14/AB36 -> -0.025375333 | AH37: TOTAL VENDOR COST | AI37: =SUM(AI30:AI36) -> 151.14 | AJ37: Sum of vendor components
E38: Founder share before tax | F38: =F36/'Simple Inputs'!$E$16 -> 29180.938 | G38: =F38*12 -> 350171.25 | H38: Founder | I38: Calculated | O38: PAYMENT LOSS
E39: Founder tax reserve | F39: =-MAX(0,F38)*'Simple Inputs'!$E$15 -> -9921.5189 | G39: =F39*12 -> -119058.23 | H39: Founder | I39: Existing assumption | O39: Line Item | P39: Monthly Subs | Q39: Annual Subs | R39: Merit Shop | S39: Total | T39: Calculation Logic
E40: FOUNDER TAKE-HOME | F40: =SUM(F38:F39) -> 19259.419 | G40: =F40*12 -> 231113.03 | H40: Founder | I40: Calculated | O40: Gross billed | P40: =$H$19 -> 69319.2 | Q40: =$H$20 -> 10199.4 | R40: =$H$21 -> 9147.5136 | S40: =SUM(P40:R40) -> 88666.114 | T40: Scenario gross billed
O41: Failed payment loss | P41: =-P40*'Simple Inputs'!$E$6 -> -3465.96 | Q41: =-Q40*'Simple Inputs'!$E$6 -> -509.97 | R41: =-R40*'Simple Inputs'!$E$6 -> -457.37568 | S41: =SUM(P41:R41) -> -4433.3057 | T41: Gross × failed-payment rate
O42: Collected after failures | P42: =SUM(P40:P41) -> 65853.24 | Q42: =SUM(Q40:Q41) -> 9689.43 | R42: =SUM(R40:R41) -> 8690.1379 | S42: =SUM(P42:R42) -> 84232.808 | T42: Gross + failed loss
O43: Refund loss | P43: =-P42*'Simple Inputs'!$E$7 -> -1975.5972 | Q43: =-Q42*'Simple Inputs'!$E$7 -> -290.6829 | R43: =-R42*'Simple Inputs'!$E$7 -> -260.70414 | S43: =SUM(P43:R43) -> -2526.9842 | T43: Collected × refund rate
O44: Post-refund volume | P44: =SUM(P42:P43) -> 63877.643 | Q44: =SUM(Q42:Q43) -> 9398.7471 | R44: =SUM(R42:R43) -> 8429.4338 | S44: =SUM(P44:R44) -> 81705.824 | T44: Collected + refund loss
O45: Chargeback principal loss | P45: =-P44*'Simple Inputs'!$E$8 -> -319.38821 | Q45: =-Q44*'Simple Inputs'!$E$8 -> -46.993735 | R45: =-R44*'Simple Inputs'!$E$8 -> -42.147169 | S45: =SUM(P45:R45) -> -408.52912 | T45: Post-refund × chargeback rate
O46: Post-chargeback volume | P46: =SUM(P44:P45) -> 63558.255 | Q46: =SUM(Q44:Q45) -> 9351.7534 | R46: =SUM(R44:R45) -> 8387.2866 | S46: =SUM(P46:R46) -> 81297.295 | T46: Post-refund + chargeback loss
O47: Stripe variable fee | P47: =-P46*'Simple Inputs'!$E$10 -> -1843.1894 | Q47: =-Q46*'Simple Inputs'!$E$10 -> -271.20085 | R47: =-R46*'Simple Inputs'!$E$10 -> -243.23131 | S47: =SUM(P47:R47) -> -2357.6215 | T47: Post-chargeback volume × variable fee
O48: Stripe fixed fee | P48: =-$F$19*(1-'Simple Inputs'!$E$6)*'Simple Inputs'!$E$11 -> -1162.8 | Q48: =-$F$20*(1-'Simple Inputs'!$E$6)*'Simple Inputs'!$E$11 -> -17.1 | R48: =-$F$21*(1-'Simple Inputs'!$E$6)*'Simple Inputs'!$E$11 -> -720.6624 | S48: =SUM(P48:R48) -> -1900.5624 | T48: Successful transactions × fixed fee
O49: Dispute fee | P49: =-$F$19*(1-'Simple Inputs'!$E$6)*(1-'Simple Inputs'!$E$7)*'Simple Inputs'!$E$8*'Simple Inputs'!$E$12 -> -281.979 | Q49: =-$F$20*(1-'Simple Inputs'!$E$6)*(1-'Simple Inputs'!$E$7)*'Simple Inputs'!$E$8*'Simple Inputs'!$E$12 -> -4.14675 | R49: =-$F$21*(1-'Simple Inputs'!$E$6)*(1-'Simple Inputs'!$E$7)*'Simple Inputs'!$E$8*'Simple Inputs'!$E$12 -> -174.76063 | S49: =SUM(P49:R49) -> -460.88638 | T49: Disputed transaction proxy × dispute fee
O50: Stripe Billing fee | P50: =-P46*IF('Simple Inputs'!$F$45="Yes",'Simple Inputs'!$I$45,0) -> 0 | Q50: =-Q46*IF('Simple Inputs'!$F$45="Yes",'Simple Inputs'!$I$45,0) -> 0 | R50: =-R46*IF('Simple Inputs'!$F$45="Yes",'Simple Inputs'!$I$45,0) -> 0 | S50: =SUM(P50:R50) -> 0 | T50: Post-chargeback volume × Billing rate when active
O51: Net cash after payments | P51: =SUM(P40,P41,P43,P45,P47:P50) -> 60270.286 | Q51: =SUM(Q40,Q41,Q43,Q45,Q47:Q50) -> 9059.3058 | R51: =SUM(R40,R41,R43,R45,R47:R50) -> 7248.6323 | S51: =SUM(P51:R51) -> 76578.224 | T51: Gross plus every loss and fee
O52: Reconciliation variance | P52: =P51-(P40+SUM(P41,P43,P45,P47:P50)) -> 0 | Q52: =Q51-(Q40+SUM(Q41,Q43,Q45,Q47:Q50)) -> 0 | R52: =R51-(R40+SUM(R41,R43,R45,R47:R50)) -> 0 | S52: =SUM(P52:R52) -> 0 | T52: Net cash minus reconstructed waterfall

Sheet Best Case
A1: BEST CASE | H1: OVERVIEW | S1: MERIT SHOP | AG1: AI COSTING
A2: SCENARIO INPUTS
A3: Total monthly users | B3: 120000
A4: Monthly Elite users | B4: 0.068 | E4: MAU tier distributions | F4: Free | G4: Elite | J4: MAU's | K4: =$B$3 -> 120000 | O4: Shop Prices | T4: Cost of features in Merits | Z4: Tokens per run - Input # | AD4: Tokens per run - Output # | AH4: Tokens per run - Cache Write # | AL4: Tokens per run - Cache Read #
A5: Annual Elite users | B5: 0.012 | E5: Monthly % | F5: =1-$B$4-$B$5 -> 0.92 | G5: =$B$4 -> 0.068 | O5: Count | P5: Price | Q5: Price per merit | T5: Features | U5: Free | V5: Elite | Z5: Features | AA5: Free | AB5: Elite | AD5: Features | AE5: Free | AF5: Elite | AH5: Features | AI5: Free | AJ5: Elite | AL5: Features | AM5: Free | AN5: Elite
E6: Annual % | F6: - | G6: =$B$5 -> 0.012 | J6: Monthly cost of plans | O6: ='Simple Inputs'!$E$27 -> 3 | P6: ='Simple Inputs'!$F$27 -> 1.99 | Q6: =P6/O6 -> 0.66333333 | T6: Resume Analysis | U6: 3 | V6: 3 | Z6: Resume Analysis | AA6: 5100 | AB6: 20000 | AD6: Resume Analysis | AE6: 4300 | AF6: 25000 | AH6: Resume Analysis | AI6: 0 | AJ6: 0 | AL6: Resume Analysis | AM6: 0 | AN6: 0
A7: MONTHLY RESULTS | E7: Monthly # | F7: =FLOOR(F5*$K$4, 1) -> 110400 | G7: =FLOOR(G5*$K$4, 1) -> 8160 | J7: Tier | K7: Free | L7: Elite | O7: ='Simple Inputs'!$E$28 -> 10 | P7: ='Simple Inputs'!$F$28 -> 4.99 | Q7: =P7/O7 -> 0.499 | T7: Career Compass | U7: 3 | V7: 3 | Z7: Linkedin Grader | AA7: 4600 | AB7: 1400 | AD7: Linkedin Grader | AE7: 5200 | AF7: 4700 | AH7: Linkedin Grader | AI7: 0 | AJ7: 4700 | AL7: Linkedin Grader | AM7: 0 | AN7: 0
A8: Revenue | B8: =$F$26 -> 173912.11 | E8: Annual # | F8: - | G8: =FLOOR(G6*$K$4, 1) -> 1440 | J8: Cost (Monthly plan) | K8: - | L8: ='Simple Inputs'!$E$13 -> 16.99 | O8: ='Simple Inputs'!$E$29 -> 25 | P8: ='Simple Inputs'!$F$29 -> 9.99 | Q8: =P8/O8 -> 0.3996 | T8: Linkedin Grader | U8: 3 | V8: 3 | Z8: Career Compass | AA8: 5300 | AB8: 14000 | AD8: Career Compass | AE8: 2500 | AF8: 6100 | AH8: Career Compass | AI8: 0 | AJ8: 0 | AL8: Career Compass | AM8: 0 | AN8: 0
A9: Payment losses | B9: =-$F$27 -> 14453.401 | E9: Annual # (monthly equivalent) | F9: - | G9: =FLOOR(G8/12, 1) -> 120 | J9: Cost (Annual plan) | K9: - | L9: ='Simple Inputs'!$E$14/12 -> 14.165833 | O9: ='Simple Inputs'!$E$30 -> 50 | P9: ='Simple Inputs'!$F$30 -> 17.99 | Q9: =P9/O9 -> 0.3598 | T9: Recruiting Lens | U9: - | V9: 5 | Z9: Recruiting Lens | AA9: - | AB9: 13000 | AD9: Recruiting Lens | AE9: - | AF9: 22000 | AH9: Recruiting Lens | AI9: - | AJ9: 0 | AL9: Recruiting Lens | AM9: - | AN9: 0
A10: Stripe fees | B10: =-$F$28 -> 9011.3316 | T10: Interview Prep Coach | U10: - | V10: - | Z10: Interview Prep Coach | AA10: - | AB10: - | AD10: Interview Prep Coach | AE10: - | AF10: - | AH10: Interview Prep Coach (standard) | AI10: - | AJ10: - | AL10: Interview Prep Coach | AM10: - | AN10: -
A11: AI costs | B11: =-$F$29 -> 15085.482 | E11: Max merit use/ month / user | J11: Stripe fees | Z11: TOTAL IINPUT TOKENS | AA11: =SUM(AA6:AA10) -> 15000 | AB11: =SUM(AB6:AB10) -> 48400 | AD11: TOTAL OUTPUT TOKENS | AE11: =SUM(AE6:AE10) -> 12000 | AF11: =SUM(AF6:AF9) -> 57800 | AH11: TOTAL CACHE-WRITE TOKENS | AI11: =SUM(AI6:AI8) -> 0 | AJ11: =SUM(AJ6:AJ9) -> 4700 | AL11: TOTAL CACHE-READ TOKENS | AM11: =SUM(AM6:AM10) -> 0 | AN11: =SUM(AN6:AN10) -> 0
A12: Document processing | B12: =-$F$30 -> 134.016 | E12: Membership | F12: Max merits / month | G12: Max cost | H12: Margin | J12: Fee type | K12: Value
A13: Software & infrastructure | B13: =-$F$31 -> 151.14 | E13: Free | F13: 10 | G13: =(AA30*AM15)+(AA31*AM16)+(AA32*AM17) -> -0.0225 | H13: - | J13: Variable fee | K13: ='Simple Inputs'!$E$10 -> 0.029 | O13: Shop Assumptions - % | T13: Shop Assumptions - $ Charged | Z13: Cost per run - Input $ | AD13: Cost per run - Output $ | AH13: Cost per run - Cache Total $ | AL13: Cost per run - TOTAL $
A14: Total monthly costs | B14: =$F$32 -> 38835.371 | E14: Elite | F14: 150 | G14: =(AB$30*AN15)+(AB$31*AN16)+(AB$32*AN17)+(AB$33*AN18) -> -1.14189 | H14: =(L8+G14)/L8 -> 0.93279046 | J14: Fixed fee | K14: ='Simple Inputs'!$E$11 -> 0.3 | O14: Tier | P14: Free | Q14: Elite | R14: Total | T14: Tier | U14: Free | V14: Elite | W14: Total | Z14: Features | AA14: Free | AB14: Elite | AD14: Features | AE14: Free | AF14: Elite | AH14: Features | AI14: Free | AJ14: Elite | AL14: Features | AM14: Free | AN14: Elite
A15: Net profit | B15: =$F$36 -> 135076.74 | O15: 3 Merits | P15: 0.025 | Q15: 0.0095 | R15: =SUM(P15:Q15) -> 0.0345 | T15: 3 Merits | U15: =(P24*P6) -> 5492.4 | V15: =Q24*$P6 -> 181.488 | W15: =SUM(U15:V15) -> 5673.888 | Z15: Resume Analysis | AA15: =AA6*$AF$29*-1 -> -0.0051 | AB15: =AB6*$AF$29*-1 -> -0.02 | AD15: Resume Analysis | AE15: =AE6*$AF$32*-1 -> -0.0215 | AF15: =AF6*$AF$32*-1 -> -0.125 | AH15: Resume Analysis | AI15: =-(AI6*$AF$30+AM6*$AF$31) -> 0 | AJ15: =-(AJ6*$AF$30+AN6*$AF$31) -> 0 | AL15: Resume Analysis | AM15: =AI15+AE15+AA15 -> -0.0266 | AN15: =AJ15+AF15+AB15 -> -0.145
A16: Profit margin | B16: =$F$37 -> 0.77669542 | E16: Stripe & AI Cost | O16: 10 Merits | P16: 0.0075 | Q16: 0.003 | R16: =SUM(P16:Q16) -> 0.0105 | T16: 10 Merits | U16: =P25*P7 -> 4131.72 | V16: =Q25*$P7 -> 143.712 | W16: =SUM(U16:V16) -> 4275.432 | Z16: Linkedin Grader | AA16: =AA7*$AF$29*-1 -> -0.0046 | AB16: =AB7*$AF$29*-1 -> -0.0014 | AD16: Linkedin Grader | AE16: =AE7*$AF$32*-1 -> -0.026 | AF16: =AF7*$AF$32*-1 -> -0.0235 | AH16: Linkedin Grader | AI16: =-(AI7*$AF$30+AM7*$AF$31) -> 0 | AJ16: =-(AJ7*$AF$30+AN7*$AF$31) -> -0.005875 | AL16: Linkedin Grader | AM16: =AI16+AE16+AA16 -> -0.0306 | AN16: =AJ16+AF16+AB16 -> -0.030775
A17: Founder take-home | B17: =$F$40 -> 44575.325 | E17: Transaction type | F17: Transactions/month | G17: Average charge | H17: Gross revenue | I17: Stripe fees | J17: AI cost | K17: Profit | O17: 25 Merits | P17: 0.0025 | Q17: 0.001 | R17: =SUM(P17:Q17) -> 0.0035 | T17: 25 Merits | U17: =P26*P8 -> 2757.24 | V17: =Q26*$P8 -> 95.904 | W17: =SUM(U17:V17) -> 2853.144 | Z17: Career Compass | AA17: =AA8*$AF$29*-1 -> -0.0053 | AB17: =AB8*$AF$29*-1 -> -0.014 | AD17: Career Compass | AE17: =AE8*$AF$32*-1 -> -0.0125 | AF17: =AF8*$AF$32*-1 -> -0.0305 | AH17: Career Compass | AI17: =-(AI8*$AF$30+AM8*$AF$31) -> 0 | AJ17: =-(AJ8*$AF$30+AN8*$AF$31) -> 0 | AL17: Career Compass | AM17: =AI17+AE17+AA17 -> -0.0178 | AN17: =AJ17+AF17+AB17 -> -0.0445
E18: Free tier usage | F18: 0 | G18: 0 | H18: 0 | I18: 0 | J18: =F7*G13 -> -2484 | K18: =SUM(H18, I18, J18) -> -2484 | O18: 50 Merits | P18: 0.001 | Q18: 0.0005 | R18: =SUM(P18:Q18) -> 0.0015 | T18: 50 Merits | U18: =P27*P9 -> 1986.096 | V18: =Q27*$P9 -> 86.352 | W18: =SUM(U18:V18) -> 2072.448 | Z18: Recruiting Lens | AA18: - | AB18: =AB9*$AF$29*-1 -> -0.013 | AD18: Recruiting Lens | AE18: - | AF18: =AF9*$AF$32*-1 -> -0.11 | AH18: Recruiting Lens | AI18: - | AJ18: =-(AJ9*$AF$30+AN9*$AF$31) -> 0 | AL18: Recruiting Lens | AM18: - | AN18: =AJ18+AF18+AB18 -> -0.123
E19: Monthly Elite subscriptions | F19: =G7 -> 8160 | G19: =L8 -> 16.99 | H19: =G19*F19 -> 138638.4 | I19: =SUM(H19*K13*-1, $K$14*F19*-1) -> -6468.5136 | J19: =G14*G7 -> -9317.8224 | K19: =SUM(H19, I19, J19) -> 122852.06 | O19: Total | P19: =SUM(P15:P18) -> 0.036 | Q19: =SUM(Q15:Q18) -> 0.014 | R19: =SUM(R15:R18) -> 0.05 | T19: Total | U19: =SUM(U15:U18) -> 14367.456 | V19: =SUM(V15:V18) -> 507.456 | W19: =SUM(W15:W18) -> 14874.912 | Z19: Interview Prep Coach | AA19: - | AB19: - | AD19: Interview Prep Coach (standard) | AE19: - | AF19: - | AH19: Interview Prep Coach (standard) | AI19: - | AJ19: - | AL19: Interview Prep Coach (standard) | AM19: - | AN19: -
E20: Annual Elite subscriptions | F20: =G9 -> 120 | G20: ='Simple Inputs'!$E$14 -> 169.99 | H20: =G20*F20 -> 20398.8 | I20: =SUM(H20*K13*-1, $K$14*F20*-1) -> -627.5652 | J20: =G14*G8 -> -1644.3216 | K20: =SUM(H20, I20, J20) -> 18126.913 | Z20: TOTAL IINPUT COST | AA20: =SUM(AA15:AA17) -> -0.015 | AB20: =SUM(AB15:AB19) -> -0.0484 | AD20: TOTAL OUTPUT COST | AE20: =SUM(AE15:AE17) -> -0.06 | AF20: =SUM(AF15:AF18) -> -0.289 | AH20: TOTAL CACHE COST | AI20: =SUM(AI15:AI17) -> 0 | AJ20: =SUM(AJ15:AJ18) -> -0.005875 | AL20: TOTAL COST | AM20: =SUM(AM15:AM17) -> -0.075 | AN20: =SUM(AN15:AN18) -> -0.343275
E21: Merit shop purchases | F21: =R28 -> 4108.8 | G21: =W19/R28 -> 3.620257 | H21: =G21*F21 -> 14874.912 | I21: =SUM(H21*K13*-1, $K$14*F21*-1) -> -1664.0124 | J21: =SUMPRODUCT($P$24:$P$27,$O$6:$O$9)*$AA$37+SUMPRODUCT($Q$24:$Q$27,$O$6:$O$9)*$AB$37 -> -267.93095 | K21: =SUM(H21, I21, J21) -> 12942.969
E22: TOTAL | F22: =SUM(F19:F21) -> 12388.8 | H22: =SUM(H19:H21) -> 173912.11 | I22: =SUM(I18:I21) -> -8760.0912 | J22: =SUM(J18:J21) -> -13714.075 | K22: =SUM(K18:K21) -> 151437.95 | O22: Shop Assumptions - Users | T22: Shop Assumptions - $ Profit | Z22: OCR COST MODEL BY TIER
O23: Tier | P23: Free | Q23: Elite | R23: Total | T23: Tier | U23: Free | V23: Elite | W23: Total | Z23: Tier | AA23: Resume Users | AB23: Resume Uploads / User | AC23: Resume Documents | AD23: Resume OCR Rate | AE23: Resume Pages / Doc | AF23: Resume OCR Pages | AG23: LinkedIn Users | AH23: LinkedIn Uploads / User | AI23: LinkedIn Documents | AJ23: LinkedIn OCR Rate | AK23: LinkedIn Pages / Doc | AL23: LinkedIn OCR Pages | AM23: Blended Cost / Page | AN23: Monthly OCR Cost
E24: Monthly Model | O24: 3 Merits | P24: =P15*$F$7 -> 2760 | Q24: =Q15*(G7+G8) -> 91.2 | R24: =SUM(P24:Q24) -> 2851.2 | T24: 3 Merits | U24: =IF(P24 = 0, 0, (P24*($P6*(1-$P$33)-$P$34-($O6*((-1*$G$13)/$AA$36))))) -> 4436.1204 | V24: =IF(Q24 = 0, 0, (Q24*($P6*(1-$P$33)-$P$34-($O6*((-1*$G$14)/$AB$36))))) -> 141.92216 | W24: =SUM(U24:V24) -> 4578.0426 | Z24: Free | AA24: =$F$7 -> 110400 | AB24: ='Simple Inputs'!$E$21 -> 1 | AC24: =AA24*AB24 -> 110400 | AD24: ='Simple Inputs'!$E$17 -> 0.1 | AE24: ='Simple Inputs'!$E$18 -> 2 | AF24: =AC24*AD24*AE24 -> 22080 | AG24: =$F$7 -> 110400 | AH24: ='Simple Inputs'!$E$23 -> 0.1 | AI24: =AG24*AH24 -> 11040 | AJ24: ='Simple Inputs'!$E$19 -> 0.1 | AK24: ='Simple Inputs'!$E$20 -> 6 | AL24: =AI24*AJ24*AK24 -> 6624 | AM24: ='Simple Inputs'!$E$38 -> 0.004 | AN24: =(AF24+AL24)*AM24 -> 114.816
E25: Line Item | F25: Monthly Amount | G25: Annualized / KPI | H25: Classification | I25: Input Status | O25: 10 Merits | P25: =P16*F7 -> 828 | Q25: =Q16*(G7+G8) -> 28.8 | R25: =SUM(P25:Q25) -> 856.8 | T25: 10 Merits | U25: =IF(P25 = 0, 0, (P25*($P7*(1-$P$33)-$P$34-($O7*((-1*$G$13)/$AA$36))))) -> 3694.5001 | V25: =IF(Q25 = 0, 0, (Q25*($P7*(1-$P$33)-$P$34-($O7*((-1*$G$14)/$AB$36))))) -> 123.59626 | W25: =SUM(U25:V25) -> 3818.0964 | Z25: Elite | AA25: =SUM($G$7:$G$8) -> 9600 | AB25: ='Simple Inputs'!$E$22 -> 1 | AC25: =AA25*AB25 -> 9600 | AD25: ='Simple Inputs'!$E$17 -> 0.1 | AE25: ='Simple Inputs'!$E$18 -> 2 | AF25: =AC25*AD25*AE25 -> 1920 | AG25: =SUM($G$7:$G$8) -> 9600 | AH25: ='Simple Inputs'!$E$24 -> 0.5 | AI25: =AG25*AH25 -> 4800 | AJ25: ='Simple Inputs'!$E$19 -> 0.1 | AK25: ='Simple Inputs'!$E$20 -> 6 | AL25: =AI25*AJ25*AK25 -> 2880 | AM25: ='Simple Inputs'!$E$39 -> 0.004 | AN25: =(AF25+AL25)*AM25 -> 19.2
E26: Gross revenue | F26: =$H$22 -> 173912.11 | G26: =F26*12 -> 2086945.3 | H26: Revenue | I26: Scenario formula | O26: 25 Merits | P26: =P17*$F$7 -> 276 | Q26: =Q17*(G7+G8) -> 9.6 | R26: =SUM(P26:Q26) -> 285.6 | T26: 25 Merits | U26: =IF(P26 = 0, 0, (P26*($P8*(1-$P$33)-$P$34-($O8*((-1*$G$13)/$AA$36))))) -> 2536.98 | V26: =IF(Q26 = 0, 0, (Q26*($P8*(1-$P$33)-$P$34-($O8*((-1*$G$14)/$AB$36))))) -> 84.152704 | W26: =SUM(U26:V26) -> 2621.1327 | Z26: Total | AA26: =SUM(AA24:AA25) -> 120000 | AB26: - | AC26: =SUM(AC24:AC25) -> 120000 | AD26: - | AE26: - | AF26: =SUM(AF24:AF25) -> 24000 | AG26: =SUM(AG24:AG25) -> 120000 | AH26: - | AI26: =SUM(AI24:AI25) -> 15840 | AJ26: - | AK26: - | AL26: =SUM(AL24:AL25) -> 9504 | AM26: - | AN26: =SUM(AN24:AN25) -> 134.016
E27: Failed payments, refunds, and chargebacks | F27: =SUM($S$41,$S$43,$S$45) -> -14453.401 | G27: =F27*12 -> -173440.81 | H27: Cost | I27: Estimate dependent | O27: 50 Merits | P27: =P18*$F$7 -> 110.4 | Q27: =Q18*(G7+G8) -> 4.8 | R27: =SUM(P27:Q27) -> 115.2 | T27: 50 Merits | U27: =IF(P27 = 0, 0, (P27*($P9*(1-$P$33)-$P$34-($O9*((-1*$G$13)/$AA$36))))) -> 1849.3792 | V27: =IF(Q27 = 0, 0, (Q27*($P9*(1-$P$33)-$P$34-($O9*((-1*$G$14)/$AB$36))))) -> 76.317712 | W27: =SUM(U27:V27) -> 1925.6969
E28: Stripe processing, fixed, dispute, and Billing fees | F28: =SUM($S$47:$S$50) -> -9011.3316 | G28: =F28*12 -> -108135.98 | H28: Cost | I28: Official rates; mix estimated | O28: Total | P28: =SUM(P24:P27) -> 3974.4 | Q28: =SUM(Q24:Q27) -> 134.4 | R28: =SUM(R24:R27) -> 4108.8 | T28: Total | U28: =SUM(U24:U27) -> 12516.98 | V28: =SUM(V24:V27) -> 425.98883 | W28: =SUM(W24:W27) -> 12942.969 | Z28: Assumed usage distribution | AD28: AI Information | AH28: VENDOR COST DETAIL
E29: AI inference including retry/failure overhead | F29: =$J$22*(1+'Simple Inputs'!$E$9) -> -15085.482 | G29: =F29*12 -> -181025.79 | H29: Cost | I29: Estimate dependent | Z29: Features | AA29: Free (10 merits) | AB29: Elite (150 merits) | AD29: Input cost | AE29: $1/1M Input Tokens | AF29: =1/1000000 -> 1e-06 | AH29: Component | AI29: Monthly Cost | AJ29: Calculation
E30: OCR processing | F30: =-$AN$26 -> -134.016 | G30: =F30*12 -> -1608.192 | H30: Cost | I30: Estimate dependent | Z30: Resume Analysis | AA30: 0.3 | AB30: 3.9 | AD30: Cache write cost | AE30: $1.25/1M Cache-Write Tokens | AF30: =1.25/1000000 -> 1.25e-06 | AH30: Supabase Pro base | AI30: ='Simple Inputs'!$P$46 -> 25 | AJ30: Central base plan
E31: Platform, domain, and developer tools | F31: =-$AI$37 -> -151.14 | G31: =F31*12 -> -1813.68 | H31: Cost | I31: Source backed; usage estimated | O31: Stripe fees | T31: Shop Prices | Z31: Linkedin Grader | AA31: 0.3 | AB31: 3.6 | AD31: Cache read cost | AE31: $0.10/1M Cache-Read Tokens | AF31: =0.1/1000000 -> 1e-07 | AH31: Supabase MAU overage | AI31: =IF('Simple Inputs'!$F$47="Yes",MAX(0,$K$4-'Simple Inputs'!$M$47)*'Simple Inputs'!$N$47,0) -> 65 | AJ31: Scenario MAU above allowance
E32: Total modeled cost | F32: =-SUM(F27:F31) -> 38835.371 | G32: =F32*12 -> 466024.45 | H32: KPI | I32: Calculated | O32: Fee type | P32: Value | T32: Count | U32: Price | Z32: Career Compass | AA32: 0.3 | AB32: 3 | AD32: Output cost | AE32: $5/1M Output Tokens | AF32: 5e-06 | AH32: Supabase other dimensions | AI32: =SUM('Simple Inputs'!$P$48:$P$55) -> 0 | AJ32: Central reference usage schedule
E33: Total modeled cost per MAU | F33: =IFERROR(F32/$K$4,0) -> 0.32362809 | G33: =F33 -> 0.32362809 | H33: KPI | I33: Calculated | O33: Variable fee | P33: ='Simple Inputs'!$E$10 -> 0.029 | T33: ='Simple Inputs'!$E$27 -> 3 | U33: ='Simple Inputs'!$F$27 -> 1.99 | Z33: Recruiting Lens | AA33: - | AB33: 2.7 | AD33: Model used for all features | AE33: claude-haiku-4-5-20251001 | AH33: Vercel Pro and usage | AI33: =SUM('Simple Inputs'!$P$56:$P$62) -> 20 | AJ33: Central reference usage schedule
E34: AI plus OCR cost per MAU | F34: =IFERROR(-(F29+F30)/$K$4,0) -> 0.12682915 | G34: =F34 -> 0.12682915 | H34: KPI | I34: Estimate dependent | O34: Fixed fee | P34: ='Simple Inputs'!$E$11 -> 0.3 | T34: ='Simple Inputs'!$E$28 -> 10 | U34: ='Simple Inputs'!$F$28 -> 4.99 | Z34: Interview Prep Coach | AA34: - | AB34: - | AH34: Domain | AI34: ='Simple Inputs'!$P$63 -> 1.14 | AJ34: Date-aware current term / renewal
E35: Vendor cost per MAU | F35: =IFERROR(-F31/$K$4,0) -> 0.0012595 | G35: =F35 -> 0.0012595 | H35: KPI | I35: Calculated | T35: ='Simple Inputs'!$E$29 -> 25 | U35: ='Simple Inputs'!$F$29 -> 9.99 | Z35: TOTAL RUNS | AA35: =SUM(AA30:AA34) -> 0.9 | AB35: =SUM(AB30:AB34) -> 13.2 | AH35: Developer tools | AI35: =SUM('Simple Inputs'!$P$64:$P$65) -> 40 | AJ35: Monthly subscriptions
E36: NET OPERATING PROFIT | F36: =SUM(F26:F31) -> 135076.74 | G36: =F36*12 -> 1620920.9 | H36: Profit | I36: Calculated | T36: ='Simple Inputs'!$E$30 -> 50 | U36: ='Simple Inputs'!$F$30 -> 17.99 | Z36: TOTAL MERITS | AA36: =(AA30*U6)+(AA31*U7)+(AA32*U8) -> 2.7 | AB36: =(AB30*V6)+(AB31*V7)+(AB32*V8)+(AB33*V9) -> 45 | AH36: Other active recurring services | AI36: =SUM('Simple Inputs'!$P$66:$P$67,'Simple Inputs'!$P$71) -> 0 | AJ36: Only explicitly activated rows
E37: Net operating margin | F37: =IFERROR(F36/F26,0) -> 0.77669542 | G37: =F37 -> 0.77669542 | H37: KPI | I37: Calculated | Z37: COST PER MERIT | AA37: =$G$13/AA36 -> -0.0083333333 | AB37: =$G$14/AB36 -> -0.025375333 | AH37: TOTAL VENDOR COST | AI37: =SUM(AI30:AI36) -> 151.14 | AJ37: Sum of vendor components
E38: Founder share before tax | F38: =F36/'Simple Inputs'!$E$16 -> 67538.371 | G38: =F38*12 -> 810460.45 | H38: Founder | I38: Calculated | O38: PAYMENT LOSS
E39: Founder tax reserve | F39: =-MAX(0,F38)*'Simple Inputs'!$E$15 -> -22963.046 | G39: =F39*12 -> -275556.55 | H39: Founder | I39: Existing assumption | O39: Line Item | P39: Monthly Subs | Q39: Annual Subs | R39: Merit Shop | S39: Total | T39: Calculation Logic
E40: FOUNDER TAKE-HOME | F40: =SUM(F38:F39) -> 44575.325 | G40: =F40*12 -> 534903.89 | H40: Founder | I40: Calculated | O40: Gross billed | P40: =$H$19 -> 138638.4 | Q40: =$H$20 -> 20398.8 | R40: =$H$21 -> 14874.912 | S40: =SUM(P40:R40) -> 173912.11 | T40: Scenario gross billed
O41: Failed payment loss | P41: =-P40*'Simple Inputs'!$E$6 -> -6931.92 | Q41: =-Q40*'Simple Inputs'!$E$6 -> -1019.94 | R41: =-R40*'Simple Inputs'!$E$6 -> -743.7456 | S41: =SUM(P41:R41) -> -8695.6056 | T41: Gross × failed-payment rate
O42: Collected after failures | P42: =SUM(P40:P41) -> 131706.48 | Q42: =SUM(Q40:Q41) -> 19378.86 | R42: =SUM(R40:R41) -> 14131.166 | S42: =SUM(P42:R42) -> 165216.51 | T42: Gross + failed loss
O43: Refund loss | P43: =-P42*'Simple Inputs'!$E$7 -> -3951.1944 | Q43: =-Q42*'Simple Inputs'!$E$7 -> -581.3658 | R43: =-R42*'Simple Inputs'!$E$7 -> -423.93499 | S43: =SUM(P43:R43) -> -4956.4952 | T43: Collected × refund rate
O44: Post-refund volume | P44: =SUM(P42:P43) -> 127755.29 | Q44: =SUM(Q42:Q43) -> 18797.494 | R44: =SUM(R42:R43) -> 13707.231 | S44: =SUM(P44:R44) -> 160260.01 | T44: Collected + refund loss
O45: Chargeback principal loss | P45: =-P44*'Simple Inputs'!$E$8 -> -638.77643 | Q45: =-Q44*'Simple Inputs'!$E$8 -> -93.987471 | R45: =-R44*'Simple Inputs'!$E$8 -> -68.536157 | S45: =SUM(P45:R45) -> -801.30006 | T45: Post-refund × chargeback rate
O46: Post-chargeback volume | P46: =SUM(P44:P45) -> 127116.51 | Q46: =SUM(Q44:Q45) -> 18703.507 | R46: =SUM(R44:R45) -> 13638.695 | S46: =SUM(P46:R46) -> 159458.71 | T46: Post-refund + chargeback loss
O47: Stripe variable fee | P47: =-P46*'Simple Inputs'!$E$10 -> -3686.3788 | Q47: =-Q46*'Simple Inputs'!$E$10 -> -542.4017 | R47: =-R46*'Simple Inputs'!$E$10 -> -395.52216 | S47: =SUM(P47:R47) -> -4624.3026 | T47: Post-chargeback volume × variable fee
O48: Stripe fixed fee | P48: =-$F$19*(1-'Simple Inputs'!$E$6)*'Simple Inputs'!$E$11 -> -2325.6 | Q48: =-$F$20*(1-'Simple Inputs'!$E$6)*'Simple Inputs'!$E$11 -> -34.2 | R48: =-$F$21*(1-'Simple Inputs'!$E$6)*'Simple Inputs'!$E$11 -> -1171.008 | S48: =SUM(P48:R48) -> -3530.808 | T48: Successful transactions × fixed fee
O49: Dispute fee | P49: =-$F$19*(1-'Simple Inputs'!$E$6)*(1-'Simple Inputs'!$E$7)*'Simple Inputs'!$E$8*'Simple Inputs'!$E$12 -> -563.958 | Q49: =-$F$20*(1-'Simple Inputs'!$E$6)*(1-'Simple Inputs'!$E$7)*'Simple Inputs'!$E$8*'Simple Inputs'!$E$12 -> -8.2935 | R49: =-$F$21*(1-'Simple Inputs'!$E$6)*(1-'Simple Inputs'!$E$7)*'Simple Inputs'!$E$8*'Simple Inputs'!$E$12 -> -283.96944 | S49: =SUM(P49:R49) -> -856.22094 | T49: Disputed transaction proxy × dispute fee
O50: Stripe Billing fee | P50: =-P46*IF('Simple Inputs'!$F$45="Yes",'Simple Inputs'!$I$45,0) -> 0 | Q50: =-Q46*IF('Simple Inputs'!$F$45="Yes",'Simple Inputs'!$I$45,0) -> 0 | R50: =-R46*IF('Simple Inputs'!$F$45="Yes",'Simple Inputs'!$I$45,0) -> 0 | S50: =SUM(P50:R50) -> 0 | T50: Post-chargeback volume × Billing rate when active
O51: Net cash after payments | P51: =SUM(P40,P41,P43,P45,P47:P50) -> 120540.57 | Q51: =SUM(Q40,Q41,Q43,Q45,Q47:Q50) -> 18118.612 | R51: =SUM(R40,R41,R43,R45,R47:R50) -> 11788.196 | S51: =SUM(P51:R51) -> 150447.38 | T51: Gross plus every loss and fee
O52: Reconciliation variance | P52: =P51-(P40+SUM(P41,P43,P45,P47:P50)) -> 0 | Q52: =Q51-(Q40+SUM(Q41,Q43,Q45,Q47:Q50)) -> 0 | R52: =R51-(R40+SUM(R41,R43,R45,R47:R50)) -> 0 | S52: =SUM(P52:R52) -> 0 | T52: Net cash minus reconstructed waterfall

Sheet Simple Inputs
A1: SIMPLE INPUTS | D1: STRIVO COSTING — SOURCES & INPUTS
A2: Defaults are filled in. Change only blue cells if needed. | D2: Model As-of Date | E2: =DATE(2026,8,1) -> 46235 | F2: Version | G2: Phase 04.1 | H2: Currency | I2: USD | J2: Last Verified | K2: =DATE(2026,8,1) -> 46235
A3: PRICING
A4: Monthly Elite price | B4: 16.99 | D4: GLOBAL OPERATING ASSUMPTIONS
A5: Annual Elite price | B5: 169.99 | D5: Input | E5: Value | F5: Unit | G5: Status | H5: Source ID | I5: Notes
D6: Failed Payment Rate | E6: =$B$8 -> 0.05 | F6: percent | G6: Estimate — production data required | H6: EST-01 | I6: Replace with unrecovered Stripe payment data.
A7: SAFETY ASSUMPTIONS | D7: Refund Rate | E7: =$B$9 -> 0.03 | F7: percent | G7: Estimate — production data required | H7: EST-01 | I7: Replace with refunds divided by collected volume.
A8: Failed payments | B8: 0.05 | D8: Chargeback Rate | E8: =$B$10 -> 0.005 | F8: percent | G8: Estimate — production data required | H8: EST-01 | I8: Replace with disputed volume divided by post-refund volume.
A9: Refunds | B9: 0.03 | D9: AI Retry and Failure Overhead | E9: =$B$11 -> 0.1 | F9: percent | G9: Estimate — production data required | H9: EST-01 | I9: Replace with telemetry cost consumed by retries and failed generations.
A10: Chargebacks | B10: 0.005 | D10: Stripe Variable Fee | E10: 0.029 | F10: percent | G10: Official | H10: STR-01 | I10: US domestic online card rate.
A11: AI cost buffer | B11: 0.1 | D11: Stripe Fixed Fee | E11: 0.3 | F11: USD/transaction | G11: Official | H11: STR-01 | I11: Per successful domestic card charge.
D12: Stripe Dispute Fee | E12: 15 | F12: USD/dispute | G12: Official | H12: STR-04 | I12: Standard US received-dispute fee.
A13: FOUNDER | D13: Monthly Elite Price | E13: =$B$4 -> 16.99 | F13: USD/month | G13: Existing model | H13: MODEL-01 | I13: Preserved current workbook price.
A14: Estimated tax rate | B14: 0.34 | D14: Annual Elite Price | E14: =$B$5 -> 169.99 | F14: USD/year | G14: Existing model | H14: MODEL-01 | I14: Annual transaction economics are calculated annually then divided by 12.
A15: Founder count | B15: 2 | D15: Founder Tax Rate | E15: =$B$14 -> 0.34 | F15: percent | G15: Existing model | H15: MODEL-01 | I15: Preserved current workbook tax assumption.
D16: Founder Count | E16: =$B$15 -> 2 | F16: founders | G16: Existing model | H16: MODEL-01 | I16: Preserved two-founder allocation.
A17: You can safely leave these defaults alone. | D17: Resume OCR Incidence | E17: 0.1 | F17: percent | G17: Estimate — production data required | H17: OCR-EST | I17: Non-zero starting estimate.
D18: Average Resume OCR Pages | E18: 2 | F18: pages/document | G18: Estimate — production data required | H18: OCR-EST | I18: Matches the current two-page resume boundary.
D19: LinkedIn OCR Incidence | E19: 0.1 | F19: percent | G19: Estimate — production data required | H19: OCR-EST | I19: Non-zero starting estimate.
D20: Average LinkedIn OCR Pages | E20: 6 | F20: pages/document | G20: Estimate — production data required | H20: OCR-EST | I20: Within the larger LinkedIn document allowance.
D21: Free Resume Uploads per User | E21: 1 | F21: uploads/month | G21: Estimate — production data required | H21: USE-EST | I21: Replace with feature usage by tier.
D22: Elite Resume Uploads per User | E22: 1 | F22: uploads/month | G22: Estimate — production data required | H22: USE-EST | I22: Replace with feature usage by tier.
D23: Free LinkedIn Uploads per User | E23: 0.1 | F23: uploads/month | G23: Estimate — production data required | H23: USE-EST | I23: Replace with feature usage by tier.
D24: Elite LinkedIn Uploads per User | E24: 0.5 | F24: uploads/month | G24: Estimate — production data required | H24: USE-EST | I24: Replace with feature usage by tier.
D25: MERIT SHOP PRICES
D26: Pack | E26: Merits | F26: Price | G26: Source ID | H26: Status | I26: Notes
D27: 3 Merits | E27: 3 | F27: 1.99 | G27: MODEL-02 | H27: Existing model | I27: Preserved current Merit pack.
D28: 10 Merits | E28: 10 | F28: 4.99 | G28: MODEL-02 | H28: Existing model | I28: Preserved current Merit pack.
D29: 25 Merits | E29: 25 | F29: 9.99 | G29: MODEL-02 | H29: Existing model | I29: Preserved current Merit pack.
D30: 50 Merits | E30: 50 | F30: 17.99 | G30: MODEL-02 | H30: Existing model | I30: Preserved current Merit pack.
D33: OCR PROVIDER BLEND
D34: Provider | E34: Status | F34: Free Share | G34: Elite Share | H34: Cost/Page | I34: Source ID | J34: Notes
D35: Mistral OCR 4 | E35: Official default estimate | F35: 1 | G35: 1 | H35: 0.004 | I35: OCR-01 | J35: Primary modeled OCR provider; replace mix with production routing.
D36: Amazon Textract Detect Text | E36: Not configured | F36: 0 | G36: 0 | H36: 0.0015 | I36: OCR-02 | J36: Visible fallback with zero share until configuration and billing are confirmed.
D37: Claude OCR | E37: Tier-gated; zero modeled share | F37: 0 | G37: 0 | H37: 0.02 | I37: ANT-01 | J37: Allowed only for Elite; replace page estimate with measured telemetry before assigning share.
D38: Free OCR Cost/Page | E38: =SUMPRODUCT(F35:F37,H35:H37) -> 0.004
D39: Elite OCR Cost/Page | E39: =SUMPRODUCT(G35:G37,H35:H37) -> 0.004
D40: Free Provider Weight Check | E40: =IF(ABS(SUM(F35:F37)-1)<0.000001,"OK","ERROR: Free OCR weights") -> OK
D41: Elite Provider Weight Check | E41: =IF(ABS(SUM(G35:G37)-1)<0.000001,"OK","ERROR: Elite OCR weights") -> OK
D43: VENDOR AND PLATFORM COST INPUTS
D44: Service | E44: Component / Plan | F44: Include? | G44: Actual Price | H44: Official / Estimated Price | I44: Active Price | J44: Active Source | K44: Billing Unit | L44: Reference Monthly Usage | M44: Included Allowance | N44: Overage Rate | O44: Billable Overage | P44: Reference Monthly Cost | Q44: Source ID | R44: Notes
D45: Stripe | E45: Billing usage-based fee | F45: No | H45: 0.007 | I45: =IF(ISNUMBER(G45),G45,H45) -> 0.007 | J45: =IF(ISNUMBER(G45),"Actual","Official / estimate") -> Official / estimate | K45: percent of eligible processed volume | L45: 0 | M45: 0 | N45: 0 | O45: =MAX(0,L45-M45) -> 0 | P45: =IF(F45="Yes",L45*I45,0) -> 0 | Q45: STR-02 | R45: Activate only if Stripe Billing is actually enabled; scenario formulas keep this at zero while Include? is No.
D46: Supabase | E46: Pro base plan | F46: Yes | H46: 25 | I46: =IF(ISNUMBER(G46),G46,H46) -> 25 | J46: =IF(ISNUMBER(G46),"Actual","Official / estimate") -> Official / estimate | K46: USD/month | L46: 0 | M46: 0 | N46: 0 | O46: =MAX(0,L46-M46) -> 0 | P46: =IF(F46="Yes",I46,0) -> 25 | Q46: SUP-01 | R46: Monthly base plan; actual invoice may replace official price in column D.
D47: Supabase | E47: Monthly Active Users | F47: Yes | H47: 0.00325 | I47: =IF(ISNUMBER(G47),G47,H47) -> 0.00325 | J47: =IF(ISNUMBER(G47),"Actual","Official / estimate") -> Official / estimate | K47: USD/MAU | L47: 120000 | M47: 100000 | N47: 0.00325 | O47: =MAX(0,L47-M47) -> 20000 | P47: =IF(F47="Yes",O47*N47,0) -> 65 | Q47: SUP-02 | R47: Reference usage is a visible planning input; scenario formulas use scenario MAU.
D48: Supabase | E48: Database disk | F48: Yes | H48: 0.125 | I48: =IF(ISNUMBER(G48),G48,H48) -> 0.125 | J48: =IF(ISNUMBER(G48),"Actual","Official / estimate") -> Official / estimate | K48: USD/GB-month | L48: 8 | M48: 8 | N48: 0.125 | O48: =MAX(0,L48-M48) -> 0 | P48: =IF(F48="Yes",O48*N48,0) -> 0 | Q48: SUP-01 | R48: Overage above included database disk.
D49: Supabase | E49: File storage | F49: Yes | H49: 0.0213 | I49: =IF(ISNUMBER(G49),G49,H49) -> 0.0213 | J49: =IF(ISNUMBER(G49),"Actual","Official / estimate") -> Official / estimate | K49: USD/GB-month | L49: 10 | M49: 100 | N49: 0.0213 | O49: =MAX(0,L49-M49) -> 0 | P49: =IF(F49="Yes",O49*N49,0) -> 0 | Q49: SUP-01 | R49: Overage above included file storage.
D50: Supabase | E50: Uncached egress | F50: Yes | H50: 0.09 | I50: =IF(ISNUMBER(G50),G50,H50) -> 0.09 | J50: =IF(ISNUMBER(G50),"Actual","Official / estimate") -> Official / estimate | K50: USD/GB | L50: 50 | M50: 250 | N50: 0.09 | O50: =MAX(0,L50-M50) -> 0 | P50: =IF(F50="Yes",O50*N50,0) -> 0 | Q50: SUP-01 | R50: Overage above included uncached egress.
D51: Supabase | E51: Cached egress | F51: Yes | H51: 0.03 | I51: =IF(ISNUMBER(G51),G51,H51) -> 0.03 | J51: =IF(ISNUMBER(G51),"Actual","Official / estimate") -> Official / estimate | K51: USD/GB | L51: 50 | M51: 250 | N51: 0.03 | O51: =MAX(0,L51-M51) -> 0 | P51: =IF(F51="Yes",O51*N51,0) -> 0 | Q51: SUP-01 | R51: Overage above included cached egress.
D52: Supabase | E52: Edge Function invocations | F52: Yes | H52: 2e-06 | I52: =IF(ISNUMBER(G52),G52,H52) -> 2e-06 | J52: =IF(ISNUMBER(G52),"Actual","Official / estimate") -> Official / estimate | K52: USD/invocation | L52: 1000000 | M52: 2000000 | N52: 2e-06 | O52: =MAX(0,L52-M52) -> 0 | P52: =IF(F52="Yes",O52*N52,0) -> 0 | Q52: SUP-01 | R52: Equivalent to $2 per million invocations above allowance.
D53: Supabase | E53: Backups | F53: Yes | H53: 0 | I53: =IF(ISNUMBER(G53),G53,H53) -> 0 | J53: =IF(ISNUMBER(G53),"Actual","Official / estimate") -> Official / estimate | K53: included | L53: 0 | M53: 0 | N53: 0 | O53: =MAX(0,L53-M53) -> 0 | P53: =IF(F53="Yes",O53*N53,0) -> 0 | Q53: SUP-01 | R53: Visible included component; verify retention and PITR selections against production.
D54: Supabase | E54: Authentication | F54: Yes | H54: 0 | I54: =IF(ISNUMBER(G54),G54,H54) -> 0 | J54: =IF(ISNUMBER(G54),"Actual","Official / estimate") -> Official / estimate | K54: modeled through MAU | L54: 0 | M54: 0 | N54: 0 | O54: =MAX(0,L54-M54) -> 0 | P54: =IF(F54="Yes",O54*N54,0) -> 0 | Q54: SUP-02 | R54: No separate duplicate cost; MAU row is the billing dimension.
D55: Supabase | E55: Logs | F55: Yes | H55: 0 | I55: =IF(ISNUMBER(G55),G55,H55) -> 0 | J55: =IF(ISNUMBER(G55),"Actual","Official / estimate") -> Official / estimate | K55: included / invoice-specific | L55: 0 | M55: 0 | N55: 0 | O55: =MAX(0,L55-M55) -> 0 | P55: =IF(F55="Yes",O55*N55,0) -> 0 | Q55: SUP-01 | R55: Visible component; replace if paid log-drain or retention charges appear.
D56: Vercel | E56: Pro base plan | F56: Yes | H56: 20 | I56: =IF(ISNUMBER(G56),G56,H56) -> 20 | J56: =IF(ISNUMBER(G56),"Actual","Official / estimate") -> Official / estimate | K56: USD/month | L56: 0 | M56: 0 | N56: 0 | O56: =MAX(0,L56-M56) -> 0 | P56: =IF(F56="Yes",I56,0) -> 20 | Q56: VER-01 | R56: Base Pro seat/plan assumption before team-seat expansion.
D57: Vercel | E57: Fast Data Transfer | F57: Yes | H57: 0.15 | I57: =IF(ISNUMBER(G57),G57,H57) -> 0.15 | J57: =IF(ISNUMBER(G57),"Actual","Official / estimate") -> Official / estimate | K57: USD/GB | L57: 200 | M57: 1024 | N57: 0.15 | O57: =MAX(0,L57-M57) -> 0 | P57: =IF(F57="Yes",O57*N57,0) -> 0 | Q57: VER-02 | R57: Reference allowance shown as 1 TB = 1024 GB.
D58: Vercel | E58: Edge Requests | F58: Yes | H58: 2e-06 | I58: =IF(ISNUMBER(G58),G58,H58) -> 2e-06 | J58: =IF(ISNUMBER(G58),"Actual","Official / estimate") -> Official / estimate | K58: USD/request | L58: 2000000 | M58: 10000000 | N58: 2e-06 | O58: =MAX(0,L58-M58) -> 0 | P58: =IF(F58="Yes",O58*N58,0) -> 0 | Q58: VER-02 | R58: Equivalent to $2 per million requests above allowance.
D59: Vercel | E59: Function Invocations | F59: Yes | H59: 6e-07 | I59: =IF(ISNUMBER(G59),G59,H59) -> 6e-07 | J59: =IF(ISNUMBER(G59),"Actual","Official / estimate") -> Official / estimate | K59: USD/invocation | L59: 500000 | M59: 1000000 | N59: 6e-07 | O59: =MAX(0,L59-M59) -> 0 | P59: =IF(F59="Yes",O59*N59,0) -> 0 | Q59: VER-02 | R59: Equivalent to $0.60 per million invocations above allowance.
D60: Vercel | E60: Image Transformations | F60: Yes | H60: 5e-05 | I60: =IF(ISNUMBER(G60),G60,H60) -> 5e-05 | J60: =IF(ISNUMBER(G60),"Actual","Official / estimate") -> Official / estimate | K60: USD/transformation | L60: 0 | M60: 5000 | N60: 5e-05 | O60: =MAX(0,L60-M60) -> 0 | P60: =IF(F60="Yes",O60*N60,0) -> 0 | Q60: VER-02 | R60: Equivalent to $0.05 per 1,000 transformations above allowance.
D61: Vercel | E61: Web Analytics | F61: Yes | H61: 0 | I61: =IF(ISNUMBER(G61),G61,H61) -> 0 | J61: =IF(ISNUMBER(G61),"Actual","Official / estimate") -> Official / estimate | K61: included / plan-dependent | L61: 0 | M61: 0 | N61: 0 | O61: =MAX(0,L61-M61) -> 0 | P61: =IF(F61="Yes",O61*N61,0) -> 0 | Q61: VER-01 | R61: Visible included component; verify production plan and overages.
D62: Vercel | E62: Speed Insights | F62: Yes | H62: 0 | I62: =IF(ISNUMBER(G62),G62,H62) -> 0 | J62: =IF(ISNUMBER(G62),"Actual","Official / estimate") -> Official / estimate | K62: included / plan-dependent | L62: 0 | M62: 0 | N62: 0 | O62: =MAX(0,L62-M62) -> 0 | P62: =IF(F62="Yes",O62*N62,0) -> 0 | Q62: VER-01 | R62: Visible included component; verify production plan and overages.
D63: Namecheap | E63: Domain registration | F63: Yes | G63: 13.68 | H63: 18.58 | I63: =IF($E$2<=DATE(2026,12,30),G63,H63) -> 13.68 | J63: =IF($E$2<=DATE(2026,12,30),"Actual current term","Official renewal") -> Actual current term | K63: USD/year | L63: 0 | M63: 0 | N63: 0 | O63: =MAX(0,L63-M63) -> 0 | P63: =IF(F63="Yes",I63/12,0) -> 1.14 | Q63: DOM-01 | R63: Actual current term through 2026-12-30; official renewal assumption applies afterward.
D64: Anthropic | E64: Claude Code Pro | F64: Yes | H64: 20 | I64: =IF(ISNUMBER(G64),G64,H64) -> 20 | J64: =IF(ISNUMBER(G64),"Actual","Official / estimate") -> Official / estimate | K64: USD/month | L64: 0 | M64: 0 | N64: 0 | O64: =MAX(0,L64-M64) -> 0 | P64: =IF(F64="Yes",I64,0) -> 20 | Q64: DEV-01 | R64: Developer tooling subscription, separate from API consumption.
D65: OpenAI | E65: ChatGPT Plus | F65: Yes | H65: 20 | I65: =IF(ISNUMBER(G65),G65,H65) -> 20 | J65: =IF(ISNUMBER(G65),"Actual","Official / estimate") -> Official / estimate | K65: USD/month | L65: 0 | M65: 0 | N65: 0 | O65: =MAX(0,L65-M65) -> 0 | P65: =IF(F65="Yes",I65,0) -> 20 | Q65: DEV-02 | R65: Developer tooling subscription, separate from production API consumption.
D66: Resend | E66: Email delivery | F66: No | H66: 0 | I66: =IF(ISNUMBER(G66),G66,H66) -> 0 | J66: =IF(ISNUMBER(G66),"Actual","Official / estimate") -> Official / estimate | K66: not configured / invoice required | L66: 0 | M66: 0 | N66: 0 | O66: =MAX(0,L66-M66) -> 0 | P66: =IF(F66="Yes",I66,0) -> 0 | Q66: EST-01 | R66: Keep visible but zero until plan and actual monthly volume are confirmed.
D67: Firecrawl | E67: Web scraping | F67: No | H67: 0 | I67: =IF(ISNUMBER(G67),G67,H67) -> 0 | J67: =IF(ISNUMBER(G67),"Actual","Official / estimate") -> Official / estimate | K67: not configured / invoice required | L67: 0 | M67: 0 | N67: 0 | O67: =MAX(0,L67-M67) -> 0 | P67: =IF(F67="Yes",I67,0) -> 0 | Q67: EST-01 | R67: Keep visible but zero until plan and actual usage are confirmed.
D68: Mistral | E68: OCR 4 | F68: No | H68: 0.004 | I68: =IF(ISNUMBER(G68),G68,H68) -> 0.004 | J68: =IF(ISNUMBER(G68),"Actual","Official / estimate") -> Official / estimate | K68: USD/page | L68: 0 | M68: 0 | N68: 0 | O68: =MAX(0,L68-M68) -> 0 | P68: =IF(F68="Yes",O68*N68,0) -> 0 | Q68: OCR-01 | R68: Modeled in the OCR provider blend; excluded here to prevent double counting.
D69: AWS | E69: Textract Detect Document Text | F69: No | H69: 0.0015 | I69: =IF(ISNUMBER(G69),G69,H69) -> 0.0015 | J69: =IF(ISNUMBER(G69),"Actual","Official / estimate") -> Official / estimate | K69: USD/page | L69: 0 | M69: 0 | N69: 0 | O69: =MAX(0,L69-M69) -> 0 | P69: =IF(F69="Yes",O69*N69,0) -> 0 | Q69: OCR-02 | R69: Modeled in the OCR provider blend; zero provider share until configured.
D70: Anthropic | E70: Production API | F70: No | H70: 0 | I70: =IF(ISNUMBER(G70),G70,H70) -> 0 | J70: =IF(ISNUMBER(G70),"Actual","Official / estimate") -> Official / estimate | K70: modeled in existing AI section | L70: 0 | M70: 0 | N70: 0 | O70: =MAX(0,L70-M70) -> 0 | P70: =IF(F70="Yes",O70*N70,0) -> 0 | Q70: ANT-01 | R70: Scenario AI feature costs already model production token economics.
D71: Other | E71: Additional recurring service | F71: No | H71: 0 | I71: =IF(ISNUMBER(G71),G71,H71) -> 0 | J71: =IF(ISNUMBER(G71),"Actual","Official / estimate") -> Official / estimate | K71: USD/month | L71: 0 | M71: 0 | N71: 0 | O71: =MAX(0,L71-M71) -> 0 | P71: =IF(F71="Yes",I71,0) -> 0 | Q71: EST-01 | R71: Placeholder for an evidenced recurring service; do not activate without source and scope.
D73: Reference Vendor Monthly Total | E73: =SUM(P45:P71) -> 151.14 | G73: Used for current-reference audit; scenario sheets recalculate MAU-sensitive costs.
D75: SOURCE AUDIT
D76: Source ID | E76: Scope | F76: Status | G76: Last Verified | H76: URL / Reference | I76: Notes
D77: STR-01 | E77: Stripe domestic online card pricing | F77: Official | G77: 46235 | H77: https://stripe.com/pricing | I77: 2.9% + $0.30 starting rate; production mix may differ.
D78: STR-02 | E78: Stripe Billing usage-based pricing | F78: Official | G78: 46235 | H78: https://stripe.com/billing/pricing | I78: 0.7% of Billing volume; model disabled until activation is confirmed.
D79: STR-03 | E79: Stripe failed-payment and recovery telemetry | F79: Production data required | G79: 46235 | H79: Stripe Dashboard / Sigma export | I79: Use unrecovered failed-payment outcomes, not generic decline benchmarks.
D80: STR-04 | E80: Stripe disputes fee | F80: Official | G80: 46235 | H80: https://stripe.com/pricing | I80: Standard US received-dispute fee modeled at $15.
D81: SUP-01 | E81: Supabase plans and usage pricing | F81: Official | G81: 46235 | H81: https://supabase.com/pricing | I81: Pro base and usage dimension rates.
D82: SUP-02 | E82: Supabase MAU billing dimension | F82: Official | G82: 46235 | H82: https://supabase.com/docs/guides/platform/manage-your-usage/monthly-active-users | I82: MAU allowance and overage treatment.
D83: VER-01 | E83: Vercel Pro plan | F83: Official | G83: 46235 | H83: https://vercel.com/pricing | I83: Pro base plan and included platform features.
D84: VER-02 | E84: Vercel usage pricing | F84: Official | G84: 46235 | H84: https://vercel.com/docs/pricing | I84: FDT, requests, functions, and image usage dimensions.
D85: OCR-01 | E85: Mistral OCR pricing | F85: Official | G85: 46235 | H85: https://mistral.ai/pricing | I85: OCR 4 modeled at $4 per 1,000 pages.
D86: OCR-02 | E86: Amazon Textract pricing | F86: Official | G86: 46235 | H86: https://aws.amazon.com/textract/pricing/ | I86: Detect Document Text modeled at $0.0015 per page for first million pages.
D87: ANT-01 | E87: Anthropic model pricing | F87: Official | G87: 46235 | H87: https://platform.claude.com/docs/en/about-claude/pricing | I87: Existing AI feature inputs remain visible on scenario sheets; replace with invoice telemetry.
D88: DEV-01 | E88: Claude Code subscription | F88: Official | G88: 46235 | H88: https://www.anthropic.com/pricing | I88: Claude Code Pro modeled at $20 per month.
... D94: OCR-EST | E94: OCR incidence, pages, and provider routing | F94: Estimate | G94: 46235 | H94: Production telemetry required | I94: Non-zero starting assumptions; replace with measured tier-level routing.
D97: PRODUCTION DATA REQUIRED
D98: # | E98: Required Input | F98: System of Record | G98: Owner | H98: Cadence | I98: Why It Matters | J98: Status
D99: 1 | E99: Production MAU by month and subscription tier | F99: Supabase Auth / profiles | G99: Product analytics | H99: Monthly | I99: Replaces scenario demand proxies and validates Supabase MAU exposure. | J99: Open
D100: 2 | E100: Supabase invoice usage by every billed dimension | F100: Supabase billing invoice | G100: Platform | H100: Monthly | I100: Confirms base plan, database, storage, egress, functions, backups, auth, and logs. | J100: Open
D101: 3 | E101: Vercel invoice usage by every billed dimension | F101: Vercel billing export | G101: Platform | H101: Monthly | I101: Confirms FDT, edge requests, functions, images, analytics, and Speed Insights. | J101: Open
D102: 4 | E102: Successfully collected Stripe volume and transaction count by payment method and geography | F102: Stripe balance transactions | G102: Finance | H102: Monthly | I102: Replaces domestic-card-only fee simplification. | J102: Open
D103: 5 | E103: Failed-payment attempts, recovered payments, and unrecovered lost volume | F103: Stripe invoices / payment intents | G103: Finance | H103: Monthly | I103: Replaces the 5% failed-payment estimate with a true loss waterfall. | J103: Open
D104: 6 | E104: Refund count and refunded principal by product | F104: Stripe refunds | G104: Finance | H104: Monthly | I104: Replaces the 3% refund estimate and supports contribution analysis. | J104: Open
D105: 7 | E105: Dispute count, disputed principal, fees, and win outcomes | F105: Stripe disputes | G105: Finance | H105: Monthly | I105: Replaces the 0.5% chargeback estimate and validates dispute fees. | J105: Open
D106: 8 | E106: Stripe Billing activation status, plan, and eligible processed volume | F106: Stripe settings and invoice | G106: Finance | H106: On change | I106: Determines whether the 0.7% Billing fee belongs in costs. | J106: Open
D107: 9 | E107: Feature usage by tier, including resume, LinkedIn, and Merit actions | F107: Application telemetry | G107: Product analytics | H107: Monthly | I107: Replaces per-user usage assumptions and ties AI/OCR demand to behavior. | J107: Open
D108: 10 | E108: AI input/output/cache tokens, model, retries, failures, and refunds by feature | F108: Anthropic usage plus internal telemetry | G108: AI platform | H108: Weekly / monthly | I108: Replaces average-call assumptions and isolates retry overhead. | J108: Open
D109: 11 | E109: OCR incidence, pages, provider, tier, retries, and failures | F109: OCR routing telemetry | G109: AI platform | H109: Weekly / monthly | I109: Replaces OCR incidence/page/provider estimates and enforces tier routing. | J109: Open
